[
  {
    "nom": "Lyon",
    "slug": "lyon",
    "codeInsee": "69123",
    "codePostal": "69001",
    "population": 519127,
    "latitude": 45.758,
    "longitude": 4.8351,
    "altitude": 173,
    "logements": 280609,
    "logementsMaison": 4,
    "prixM2Moyen": 5240,
    "menuisiersRGE": 64,
    "tauxRenovation": "2.4",
    "intercommunalite": "Métropole de Lyon",
    "canton": "Lyon (Lyon)",
    "distanceLyon": 0.7,
    "windExposure": "Modéré à Fort (Couloir rhodanien et vents du Nord/Sud en hauteur)",
    "secteurSauvegarde": true,
    "profilCommune": "métropole majeure régionale et capitale des Gaules",
    "marcheImmobilier": "très haut de gamme (Lyon centre, Monts d'Or)",
    "tauxMaisonLabel": "très dense et à forte dominante d'habitat collectif (cœur de métropole)"
  },
  {
    "nom": "Villeurbanne",
    "slug": "villeurbanne",
    "codeInsee": "69266",
    "codePostal": "69100",
    "population": 163684,
    "latitude": 45.7719,
    "longitude": 4.8898,
    "altitude": 170,
    "logements": 79846,
    "logementsMaison": 8,
    "prixM2Moyen": 4090,
    "menuisiersRGE": 29,
    "tauxRenovation": "2.6",
    "intercommunalite": "Métropole de Lyon",
    "canton": "Villeurbanne",
    "distanceLyon": 4.3,
    "windExposure": "Modéré à Fort (Couloir rhodanien et vents du Nord/Sud en hauteur)",
    "secteurSauvegarde": false,
    "profilCommune": "deuxième commune du département et pôle urbain dynamique",
    "marcheImmobilier": "très dynamique et résidentiel recherché",
    "tauxMaisonLabel": "très dense et à forte dominante d'habitat collectif (cœur de métropole)"
  },
  {
    "nom": "Vénissieux",
    "slug": "venissieux",
    "codeInsee": "69259",
    "codePostal": "69200",
    "population": 65502,
    "latitude": 45.7012,
    "longitude": 4.8805,
    "altitude": 186,
    "logements": 31952,
    "logementsMaison": 20,
    "prixM2Moyen": 2370,
    "menuisiersRGE": 15,
    "tauxRenovation": "2.8",
    "intercommunalite": "Métropole de Lyon",
    "canton": "Vénissieux",
    "distanceLyon": 7.8,
    "windExposure": "Modéré (Protégé par les collines ou en fond de vallée)",
    "secteurSauvegarde": false,
    "profilCommune": "ville moyenne dynamique et pôle d'activité majeur",
    "marcheImmobilier": "accessible et attractif",
    "tauxMaisonLabel": "majoritairement collectif avec résidences et immeubles récents"
  },
  {
    "nom": "Vaulx-en-Velin",
    "slug": "vaulx-en-velin",
    "codeInsee": "69256",
    "codePostal": "69120",
    "population": 53069,
    "latitude": 45.7776,
    "longitude": 4.925,
    "altitude": 168,
    "logements": 25887,
    "logementsMaison": 22,
    "prixM2Moyen": 2620,
    "menuisiersRGE": 14,
    "tauxRenovation": "2.1",
    "intercommunalite": "Métropole de Lyon",
    "canton": "Canton de Vaulx-en-Velin",
    "distanceLyon": 7.1,
    "windExposure": "Modéré (Plaine de l'Est Lyonnais)",
    "secteurSauvegarde": false,
    "profilCommune": "ville moyenne dynamique et pôle d'activité majeur",
    "marcheImmobilier": "accessible et attractif",
    "tauxMaisonLabel": "majoritairement collectif avec résidences et immeubles récents"
  },
  {
    "nom": "Saint-Priest",
    "slug": "saint-priest",
    "codeInsee": "69290",
    "codePostal": "69800",
    "population": 49229,
    "latitude": 45.7014,
    "longitude": 4.9474,
    "altitude": 208,
    "logements": 24014,
    "logementsMaison": 30,
    "prixM2Moyen": 3100,
    "menuisiersRGE": 14,
    "tauxRenovation": "2.5",
    "intercommunalite": "Métropole de Lyon",
    "canton": "Canton de Saint-Priest",
    "distanceLyon": 11.1,
    "windExposure": "Modéré (Plaine de l'Est Lyonnais)",
    "secteurSauvegarde": false,
    "profilCommune": "ville moyenne dynamique et pôle d'activité majeur",
    "marcheImmobilier": "intermédiaire et stable",
    "tauxMaisonLabel": "majoritairement collectif avec résidences et immeubles récents"
  },
  {
    "nom": "Caluire-et-Cuire",
    "slug": "caluire-et-cuire",
    "codeInsee": "69034",
    "codePostal": "69300",
    "population": 43597,
    "latitude": 45.7986,
    "longitude": 4.8494,
    "altitude": 250,
    "logements": 21267,
    "logementsMaison": 29,
    "prixM2Moyen": 4070,
    "menuisiersRGE": 15,
    "tauxRenovation": "2.7",
    "intercommunalite": "Métropole de Lyon",
    "canton": "Caluire-et-Cuire",
    "distanceLyon": 4,
    "windExposure": "Modéré à Fort (Couloir rhodanien et vents du Nord/Sud en hauteur)",
    "secteurSauvegarde": false,
    "profilCommune": "ville moyenne dynamique et pôle d'activité majeur",
    "marcheImmobilier": "très dynamique et résidentiel recherché",
    "tauxMaisonLabel": "majoritairement collectif avec résidences et immeubles récents"
  },
  {
    "nom": "Bron",
    "slug": "bron",
    "codeInsee": "69029",
    "codePostal": "69500",
    "population": 42982,
    "latitude": 45.7355,
    "longitude": 4.9116,
    "altitude": 210,
    "logements": 20967,
    "logementsMaison": 36,
    "prixM2Moyen": 3510,
    "menuisiersRGE": 15,
    "tauxRenovation": "2.8",
    "intercommunalite": "Métropole de Lyon",
    "canton": "Canton de Bron",
    "distanceLyon": 6.7,
    "windExposure": "Modéré (Plaine de l'Est Lyonnais)",
    "secteurSauvegarde": false,
    "profilCommune": "ville moyenne dynamique et pôle d'activité majeur",
    "marcheImmobilier": "intermédiaire et stable",
    "tauxMaisonLabel": "majoritairement collectif avec résidences et immeubles récents"
  },
  {
    "nom": "Oullins-Pierre-Bénite",
    "slug": "oullins-pierre-benite",
    "codeInsee": "69149",
    "codePostal": "69310",
    "population": 38168,
    "latitude": 45.708,
    "longitude": 4.8112,
    "altitude": 150,
    "logements": 16964,
    "logementsMaison": 69,
    "prixM2Moyen": 3150,
    "menuisiersRGE": 9,
    "tauxRenovation": "2.9",
    "intercommunalite": "Communauté de Communes des Monts du Lyonnais",
    "canton": "Canton de Oullins-Pierre-Bénite",
    "distanceLyon": 6.5,
    "windExposure": "Modéré (Protégé par les collines ou en fond de vallée)",
    "secteurSauvegarde": false,
    "profilCommune": "ville moyenne dynamique et pôle d'activité majeur",
    "marcheImmobilier": "intermédiaire et stable",
    "tauxMaisonLabel": "principalement composé de maisons individuelles et pavillons"
  },
  {
    "nom": "Meyzieu",
    "slug": "meyzieu",
    "codeInsee": "69282",
    "codePostal": "69330",
    "population": 36687,
    "latitude": 45.7785,
    "longitude": 5.0114,
    "altitude": 190,
    "logements": 16305,
    "logementsMaison": 63,
    "prixM2Moyen": 3200,
    "menuisiersRGE": 10,
    "tauxRenovation": "2.1",
    "intercommunalite": "Métropole de Lyon",
    "canton": "Canton de Meyzieu",
    "distanceLyon": 13.7,
    "windExposure": "Modéré (Plaine de l'Est Lyonnais)",
    "secteurSauvegarde": false,
    "profilCommune": "ville moyenne dynamique et pôle d'activité majeur",
    "marcheImmobilier": "intermédiaire et stable",
    "tauxMaisonLabel": "principalement composé de maisons individuelles et pavillons"
  },
  {
    "nom": "Villefranche-sur-Saône",
    "slug": "villefranche-sur-saone",
    "codeInsee": "69264",
    "codePostal": "69400",
    "population": 36172,
    "latitude": 45.9837,
    "longitude": 4.726,
    "altitude": 191,
    "logements": 16076,
    "logementsMaison": 68,
    "prixM2Moyen": 3160,
    "menuisiersRGE": 9,
    "tauxRenovation": "2.5",
    "intercommunalite": "Communauté d'Agglomération de Villefranche Beaujolais Saône",
    "canton": "Villefranche-sur-Saône",
    "distanceLyon": 25.9,
    "windExposure": "Modéré (Protégé par les collines ou en fond de vallée)",
    "secteurSauvegarde": true,
    "profilCommune": "capitale historique du Beaujolais et sous-préfecture du Rhône",
    "marcheImmobilier": "intermédiaire et stable",
    "tauxMaisonLabel": "principalement composé de maisons individuelles et pavillons"
  },
  {
    "nom": "Rillieux-la-Pape",
    "slug": "rillieux-la-pape",
    "codeInsee": "69286",
    "codePostal": "69140",
    "population": 31389,
    "latitude": 45.8265,
    "longitude": 4.895,
    "altitude": 268,
    "logements": 13951,
    "logementsMaison": 34,
    "prixM2Moyen": 3410,
    "menuisiersRGE": 8,
    "tauxRenovation": "2.5",
    "intercommunalite": "Métropole de Lyon",
    "canton": "Canton de Rillieux-la-Pape",
    "distanceLyon": 8.3,
    "windExposure": "Modéré (Protégé par les collines ou en fond de vallée)",
    "secteurSauvegarde": false,
    "profilCommune": "ville moyenne dynamique et pôle d'activité majeur",
    "marcheImmobilier": "intermédiaire et stable",
    "tauxMaisonLabel": "majoritairement collectif avec résidences et immeubles récents"
  },
  {
    "nom": "Décines-Charpieu",
    "slug": "decines-charpieu",
    "codeInsee": "69275",
    "codePostal": "69150",
    "population": 29877,
    "latitude": 45.7759,
    "longitude": 4.9589,
    "altitude": 188,
    "logements": 13279,
    "logementsMaison": 36,
    "prixM2Moyen": 3180,
    "menuisiersRGE": 10,
    "tauxRenovation": "2.7",
    "intercommunalite": "Métropole de Lyon",
    "canton": "Canton de Décines-Charpieu",
    "distanceLyon": 9.6,
    "windExposure": "Modéré (Plaine de l'Est Lyonnais)",
    "secteurSauvegarde": false,
    "profilCommune": "ville périurbaine résidentielle et commerçante du lyonnais",
    "marcheImmobilier": "intermédiaire et stable",
    "tauxMaisonLabel": "majoritairement collectif avec résidences et immeubles récents"
  },
  {
    "nom": "Tassin-la-Demi-Lune",
    "slug": "tassin-la-demi-lune",
    "codeInsee": "69244",
    "codePostal": "69160",
    "population": 23200,
    "latitude": 45.7637,
    "longitude": 4.7521,
    "altitude": 220,
    "logements": 10311,
    "logementsMaison": 70,
    "prixM2Moyen": 6290,
    "menuisiersRGE": 8,
    "tauxRenovation": "2.2",
    "intercommunalite": "Métropole de Lyon",
    "canton": "Canton de Tassin-la-Demi-Lune",
    "distanceLyon": 6.5,
    "windExposure": "Modéré (Protégé par les collines ou en fond de vallée)",
    "secteurSauvegarde": false,
    "profilCommune": "ville périurbaine résidentielle et commerçante du lyonnais",
    "marcheImmobilier": "très haut de gamme (Lyon centre, Monts d'Or)",
    "tauxMaisonLabel": "principalement composé de maisons individuelles et pavillons"
  },
  {
    "nom": "Sainte-Foy-lès-Lyon",
    "slug": "sainte-foy-les-lyon",
    "codeInsee": "69202",
    "codePostal": "69110",
    "population": 21692,
    "latitude": 45.7362,
    "longitude": 4.7926,
    "altitude": 300,
    "logements": 9641,
    "logementsMaison": 68,
    "prixM2Moyen": 6290,
    "menuisiersRGE": 8,
    "tauxRenovation": "2.1",
    "intercommunalite": "Métropole de Lyon",
    "canton": "Canton de Sainte-Foy-lès-Lyon",
    "distanceLyon": 4.6,
    "windExposure": "Modéré (Protégé par les collines ou en fond de vallée)",
    "secteurSauvegarde": false,
    "profilCommune": "ville périurbaine résidentielle et commerçante du lyonnais",
    "marcheImmobilier": "très haut de gamme (Lyon centre, Monts d'Or)",
    "tauxMaisonLabel": "principalement composé de maisons individuelles et pavillons"
  },
  {
    "nom": "Givors",
    "slug": "givors",
    "codeInsee": "69091",
    "codePostal": "69700",
    "population": 21379,
    "latitude": 45.5845,
    "longitude": 4.7561,
    "altitude": 160,
    "logements": 9502,
    "logementsMaison": 63,
    "prixM2Moyen": 2430,
    "menuisiersRGE": 8,
    "tauxRenovation": "2.8",
    "intercommunalite": "Métropole de Lyon",
    "canton": "Canton de Givors",
    "distanceLyon": 20.9,
    "windExposure": "Modéré (Protégé par les collines ou en fond de vallée)",
    "secteurSauvegarde": false,
    "profilCommune": "ville périurbaine résidentielle et commerçante du lyonnais",
    "marcheImmobilier": "accessible et attractif",
    "tauxMaisonLabel": "principalement composé de maisons individuelles et pavillons"
  },
  {
    "nom": "Saint-Genis-Laval",
    "slug": "saint-genis-laval",
    "codeInsee": "69204",
    "codePostal": "69230",
    "population": 21212,
    "latitude": 45.6922,
    "longitude": 4.7929,
    "altitude": 220,
    "logements": 9428,
    "logementsMaison": 60,
    "prixM2Moyen": 4090,
    "menuisiersRGE": 8,
    "tauxRenovation": "2.7",
    "intercommunalite": "Métropole de Lyon",
    "canton": "Canton de Saint-Genis-Laval",
    "distanceLyon": 8.7,
    "windExposure": "Modéré (Protégé par les collines ou en fond de vallée)",
    "secteurSauvegarde": false,
    "profilCommune": "ville périurbaine résidentielle et commerçante du lyonnais",
    "marcheImmobilier": "très dynamique et résidentiel recherché",
    "tauxMaisonLabel": "principalement composé de maisons individuelles et pavillons"
  },
  {
    "nom": "Saint-Fons",
    "slug": "saint-fons",
    "codeInsee": "69199",
    "codePostal": "69190",
    "population": 19285,
    "latitude": 45.6997,
    "longitude": 4.8514,
    "altitude": 165,
    "logements": 8571,
    "logementsMaison": 21,
    "prixM2Moyen": 2470,
    "menuisiersRGE": 5,
    "tauxRenovation": "2.7",
    "intercommunalite": "Métropole de Lyon",
    "canton": "Canton de Saint-Fons",
    "distanceLyon": 7.3,
    "windExposure": "Modéré (Protégé par les collines ou en fond de vallée)",
    "secteurSauvegarde": false,
    "profilCommune": "ville périurbaine résidentielle et commerçante du lyonnais",
    "marcheImmobilier": "accessible et attractif",
    "tauxMaisonLabel": "majoritairement collectif avec résidences et immeubles récents"
  },
  {
    "nom": "Écully",
    "slug": "ecully",
    "codeInsee": "69081",
    "codePostal": "69130",
    "population": 17944,
    "latitude": 45.7822,
    "longitude": 4.7737,
    "altitude": 240,
    "logements": 7975,
    "logementsMaison": 60,
    "prixM2Moyen": 6590,
    "menuisiersRGE": 5,
    "tauxRenovation": "2.5",
    "intercommunalite": "Métropole de Lyon",
    "canton": "Canton de Écully",
    "distanceLyon": 5.2,
    "windExposure": "Modéré (Protégé par les collines ou en fond de vallée)",
    "secteurSauvegarde": false,
    "profilCommune": "ville périurbaine résidentielle et commerçante du lyonnais",
    "marcheImmobilier": "très haut de gamme (Lyon centre, Monts d'Or)",
    "tauxMaisonLabel": "principalement composé de maisons individuelles et pavillons"
  },
  {
    "nom": "Francheville",
    "slug": "francheville",
    "codeInsee": "69089",
    "codePostal": "69340",
    "population": 15604,
    "latitude": 45.7386,
    "longitude": 4.7537,
    "altitude": 260,
    "logements": 6935,
    "logementsMaison": 64,
    "prixM2Moyen": 3520,
    "menuisiersRGE": 5,
    "tauxRenovation": "2.5",
    "intercommunalite": "Métropole de Lyon",
    "canton": "Canton de Francheville",
    "distanceLyon": 7,
    "windExposure": "Modéré (Protégé par les collines ou en fond de vallée)",
    "secteurSauvegarde": false,
    "profilCommune": "ville périurbaine résidentielle et commerçante du lyonnais",
    "marcheImmobilier": "intermédiaire et stable",
    "tauxMaisonLabel": "principalement composé de maisons individuelles et pavillons"
  },
  {
    "nom": "Belleville-en-Beaujolais",
    "slug": "belleville-en-beaujolais",
    "codeInsee": "69019",
    "codePostal": "69220",
    "population": 14016,
    "latitude": 46.1145,
    "longitude": 4.7291,
    "altitude": 191,
    "logements": 6229,
    "logementsMaison": 61,
    "prixM2Moyen": 3280,
    "menuisiersRGE": 5,
    "tauxRenovation": "2.4",
    "intercommunalite": "Communauté de Communes Saône Beaujolais",
    "canton": "Canton de Belleville-en-Beaujolais",
    "distanceLyon": 39.8,
    "windExposure": "Modéré (Protégé par les collines ou en fond de vallée)",
    "secteurSauvegarde": false,
    "profilCommune": "ville périurbaine résidentielle et commerçante du lyonnais",
    "marcheImmobilier": "intermédiaire et stable",
    "tauxMaisonLabel": "principalement composé de maisons individuelles et pavillons"
  },
  {
    "nom": "Mions",
    "slug": "mions",
    "codeInsee": "69283",
    "codePostal": "69780",
    "population": 13843,
    "latitude": 45.6628,
    "longitude": 4.9467,
    "altitude": 210,
    "logements": 6152,
    "logementsMaison": 67,
    "prixM2Moyen": 3400,
    "menuisiersRGE": 7,
    "tauxRenovation": "2.5",
    "intercommunalite": "Métropole de Lyon",
    "canton": "Canton de Mions",
    "distanceLyon": 14.2,
    "windExposure": "Modéré (Plaine de l'Est Lyonnais)",
    "secteurSauvegarde": false,
    "profilCommune": "ville périurbaine résidentielle et commerçante du lyonnais",
    "marcheImmobilier": "intermédiaire et stable",
    "tauxMaisonLabel": "principalement composé de maisons individuelles et pavillons"
  },
  {
    "nom": "Genas",
    "slug": "genas",
    "codeInsee": "69277",
    "codePostal": "69740",
    "population": 13421,
    "latitude": 45.7286,
    "longitude": 5.0172,
    "altitude": 225,
    "logements": 5965,
    "logementsMaison": 61,
    "prixM2Moyen": 4210,
    "menuisiersRGE": 7,
    "tauxRenovation": "2.8",
    "intercommunalite": "Communauté de Communes de l'Est Lyonnais",
    "canton": "Canton de Genas",
    "distanceLyon": 14.6,
    "windExposure": "Modéré (Plaine de l'Est Lyonnais)",
    "secteurSauvegarde": false,
    "profilCommune": "ville périurbaine résidentielle et commerçante du lyonnais",
    "marcheImmobilier": "très dynamique et résidentiel recherché",
    "tauxMaisonLabel": "principalement composé de maisons individuelles et pavillons"
  },
  {
    "nom": "Brignais",
    "slug": "brignais",
    "codeInsee": "69027",
    "codePostal": "69530",
    "population": 12503,
    "latitude": 45.6751,
    "longitude": 4.7527,
    "altitude": 230,
    "logements": 5557,
    "logementsMaison": 68,
    "prixM2Moyen": 3150,
    "menuisiersRGE": 6,
    "tauxRenovation": "2.2",
    "intercommunalite": "Communauté de Communes de la Vallée du Garon",
    "canton": "Canton de Brignais",
    "distanceLyon": 11.8,
    "windExposure": "Modéré (Protégé par les collines ou en fond de vallée)",
    "secteurSauvegarde": false,
    "profilCommune": "ville périurbaine résidentielle et commerçante du lyonnais",
    "marcheImmobilier": "intermédiaire et stable",
    "tauxMaisonLabel": "principalement composé de maisons individuelles et pavillons"
  },
  {
    "nom": "Craponne",
    "slug": "craponne",
    "codeInsee": "69069",
    "codePostal": "69290",
    "population": 12084,
    "latitude": 45.7456,
    "longitude": 4.7294,
    "altitude": 280,
    "logements": 5371,
    "logementsMaison": 65,
    "prixM2Moyen": 3100,
    "menuisiersRGE": 7,
    "tauxRenovation": "2.9",
    "intercommunalite": "Communauté de Communes des Vallons du Lyonnais",
    "canton": "Canton de Craponne",
    "distanceLyon": 8.5,
    "windExposure": "Modéré (Protégé par les collines ou en fond de vallée)",
    "secteurSauvegarde": false,
    "profilCommune": "ville périurbaine résidentielle et commerçante du lyonnais",
    "marcheImmobilier": "intermédiaire et stable",
    "tauxMaisonLabel": "principalement composé de maisons individuelles et pavillons"
  },
  {
    "nom": "Corbas",
    "slug": "corbas",
    "codeInsee": "69273",
    "codePostal": "69960",
    "population": 11315,
    "latitude": 45.6654,
    "longitude": 4.9104,
    "altitude": 200,
    "logements": 5029,
    "logementsMaison": 65,
    "prixM2Moyen": 3560,
    "menuisiersRGE": 7,
    "tauxRenovation": "2.4",
    "intercommunalite": "Métropole de Lyon",
    "canton": "Canton de Corbas",
    "distanceLyon": 12.4,
    "windExposure": "Modéré (Plaine de l'Est Lyonnais)",
    "secteurSauvegarde": false,
    "profilCommune": "ville périurbaine résidentielle et commerçante du lyonnais",
    "marcheImmobilier": "intermédiaire et stable",
    "tauxMaisonLabel": "principalement composé de maisons individuelles et pavillons"
  },
  {
    "nom": "Chassieu",
    "slug": "chassieu",
    "codeInsee": "69271",
    "codePostal": "69680",
    "population": 11208,
    "latitude": 45.7366,
    "longitude": 4.9638,
    "altitude": 200,
    "logements": 4981,
    "logementsMaison": 66,
    "prixM2Moyen": 3160,
    "menuisiersRGE": 6,
    "tauxRenovation": "2.5",
    "intercommunalite": "Métropole de Lyon",
    "canton": "Canton de Chassieu",
    "distanceLyon": 10.4,
    "windExposure": "Modéré (Plaine de l'Est Lyonnais)",
    "secteurSauvegarde": false,
    "profilCommune": "ville périurbaine résidentielle et commerçante du lyonnais",
    "marcheImmobilier": "intermédiaire et stable",
    "tauxMaisonLabel": "principalement composé de maisons individuelles et pavillons"
  },
  {
    "nom": "Tarare",
    "slug": "tarare",
    "codeInsee": "69243",
    "codePostal": "69170",
    "population": 10893,
    "latitude": 45.9071,
    "longitude": 4.4302,
    "altitude": 380,
    "logements": 4841,
    "logementsMaison": 81,
    "prixM2Moyen": 2670,
    "menuisiersRGE": 5,
    "tauxRenovation": "2.2",
    "intercommunalite": "Communauté de Communes de l'Ouest Rhodanien",
    "canton": "Canton de Tarare",
    "distanceLyon": 35.2,
    "windExposure": "Élevé (Monts du Lyonnais et coteaux exposés)",
    "secteurSauvegarde": false,
    "profilCommune": "ville périurbaine résidentielle et commerçante du lyonnais",
    "marcheImmobilier": "accessible et attractif",
    "tauxMaisonLabel": "très majoritairement composé de villas contemporaines et maisons de village"
  },
  {
    "nom": "Feyzin",
    "slug": "feyzin",
    "codeInsee": "69276",
    "codePostal": "69320",
    "population": 10304,
    "latitude": 45.6736,
    "longitude": 4.8589,
    "altitude": 210,
    "logements": 4580,
    "logementsMaison": 62,
    "prixM2Moyen": 3470,
    "menuisiersRGE": 7,
    "tauxRenovation": "2.1",
    "intercommunalite": "Métropole de Lyon",
    "canton": "Canton de Feyzin",
    "distanceLyon": 10.2,
    "windExposure": "Modéré (Protégé par les collines ou en fond de vallée)",
    "secteurSauvegarde": false,
    "profilCommune": "ville périurbaine résidentielle et commerçante du lyonnais",
    "marcheImmobilier": "intermédiaire et stable",
    "tauxMaisonLabel": "principalement composé de maisons individuelles et pavillons"
  },
  {
    "nom": "Grigny-sur-Rhône",
    "slug": "grigny-sur-rhone",
    "codeInsee": "69096",
    "codePostal": "69520",
    "population": 10030,
    "latitude": 45.6104,
    "longitude": 4.7858,
    "altitude": 218,
    "logements": 4458,
    "logementsMaison": 63,
    "prixM2Moyen": 3470,
    "menuisiersRGE": 6,
    "tauxRenovation": "2.6",
    "intercommunalite": "Communauté de Communes des Monts du Lyonnais",
    "canton": "Canton de Grigny-sur-Rhône",
    "distanceLyon": 17.5,
    "windExposure": "Modéré (Protégé par les collines ou en fond de vallée)",
    "secteurSauvegarde": false,
    "profilCommune": "ville périurbaine résidentielle et commerçante du lyonnais",
    "marcheImmobilier": "intermédiaire et stable",
    "tauxMaisonLabel": "principalement composé de maisons individuelles et pavillons"
  },
  {
    "nom": "Chaponost",
    "slug": "chaponost",
    "codeInsee": "69043",
    "codePostal": "69630",
    "population": 9382,
    "latitude": 45.7089,
    "longitude": 4.7452,
    "altitude": 290,
    "logements": 4170,
    "logementsMaison": 68,
    "prixM2Moyen": 3570,
    "menuisiersRGE": 4,
    "tauxRenovation": "2.4",
    "intercommunalite": "Communauté de Communes des Vallons du Lyonnais",
    "canton": "Canton de Chaponost",
    "distanceLyon": 9.3,
    "windExposure": "Modéré (Protégé par les collines ou en fond de vallée)",
    "secteurSauvegarde": false,
    "profilCommune": "bourg rhodanien ou beaujolais typique",
    "marcheImmobilier": "intermédiaire et stable",
    "tauxMaisonLabel": "principalement composé de maisons individuelles et pavillons"
  },
  {
    "nom": "Dardilly",
    "slug": "dardilly",
    "codeInsee": "69072",
    "codePostal": "69570",
    "population": 9221,
    "latitude": 45.8133,
    "longitude": 4.7466,
    "altitude": 267,
    "logements": 4098,
    "logementsMaison": 64,
    "prixM2Moyen": 3350,
    "menuisiersRGE": 2,
    "tauxRenovation": "2.7",
    "intercommunalite": "Métropole de Lyon",
    "canton": "Canton de Dardilly",
    "distanceLyon": 8.8,
    "windExposure": "Modéré (Protégé par les collines ou en fond de vallée)",
    "secteurSauvegarde": false,
    "profilCommune": "bourg rhodanien ou beaujolais typique",
    "marcheImmobilier": "intermédiaire et stable",
    "tauxMaisonLabel": "principalement composé de maisons individuelles et pavillons"
  },
  {
    "nom": "Irigny",
    "slug": "irigny",
    "codeInsee": "69100",
    "codePostal": "69540",
    "population": 9034,
    "latitude": 45.6747,
    "longitude": 4.8143,
    "altitude": 196,
    "logements": 4015,
    "logementsMaison": 65,
    "prixM2Moyen": 3500,
    "menuisiersRGE": 4,
    "tauxRenovation": "2.1",
    "intercommunalite": "Métropole de Lyon",
    "canton": "Canton de Irigny",
    "distanceLyon": 10.1,
    "windExposure": "Modéré (Protégé par les collines ou en fond de vallée)",
    "secteurSauvegarde": false,
    "profilCommune": "bourg rhodanien ou beaujolais typique",
    "marcheImmobilier": "intermédiaire et stable",
    "tauxMaisonLabel": "principalement composé de maisons individuelles et pavillons"
  },
  {
    "nom": "Anse",
    "slug": "anse",
    "codeInsee": "69009",
    "codePostal": "69480",
    "population": 8206,
    "latitude": 45.9451,
    "longitude": 4.7049,
    "altitude": 150,
    "logements": 3647,
    "logementsMaison": 64,
    "prixM2Moyen": 3490,
    "menuisiersRGE": 2,
    "tauxRenovation": "2.4",
    "intercommunalite": "Communauté de Communes Beaujolais Pierres Dorées",
    "canton": "Canton de Anse",
    "distanceLyon": 22.5,
    "windExposure": "Modéré (Protégé par les collines ou en fond de vallée)",
    "secteurSauvegarde": true,
    "profilCommune": "bourg rhodanien ou beaujolais typique",
    "marcheImmobilier": "intermédiaire et stable",
    "tauxMaisonLabel": "principalement composé de maisons individuelles et pavillons"
  },
  {
    "nom": "Gleizé",
    "slug": "gleize",
    "codeInsee": "69092",
    "codePostal": "69400",
    "population": 8035,
    "latitude": 45.9915,
    "longitude": 4.6883,
    "altitude": 214,
    "logements": 3571,
    "logementsMaison": 71,
    "prixM2Moyen": 3320,
    "menuisiersRGE": 4,
    "tauxRenovation": "2.1",
    "intercommunalite": "Communauté d'Agglomération de Villefranche Beaujolais Saône",
    "canton": "Villefranche-sur-Saône",
    "distanceLyon": 27.7,
    "windExposure": "Élevé (Monts du Lyonnais et coteaux exposés)",
    "secteurSauvegarde": false,
    "profilCommune": "bourg rhodanien ou beaujolais typique",
    "marcheImmobilier": "intermédiaire et stable",
    "tauxMaisonLabel": "principalement composé de maisons individuelles et pavillons"
  },
  {
    "nom": "Neuville-sur-Saône",
    "slug": "neuville-sur-saone",
    "codeInsee": "69143",
    "codePostal": "69250",
    "population": 7812,
    "latitude": 45.8821,
    "longitude": 4.8404,
    "altitude": 190,
    "logements": 3472,
    "logementsMaison": 71,
    "prixM2Moyen": 3590,
    "menuisiersRGE": 4,
    "tauxRenovation": "2.6",
    "intercommunalite": "Métropole de Lyon",
    "canton": "Canton de Neuville-sur-Saône",
    "distanceLyon": 13.1,
    "windExposure": "Modéré (Protégé par les collines ou en fond de vallée)",
    "secteurSauvegarde": false,
    "profilCommune": "bourg rhodanien ou beaujolais typique",
    "marcheImmobilier": "intermédiaire et stable",
    "tauxMaisonLabel": "principalement composé de maisons individuelles et pavillons"
  },
  {
    "nom": "Saint-Didier-au-Mont-d'Or",
    "slug": "saint-didier-au-mont-d-or",
    "codeInsee": "69194",
    "codePostal": "69370",
    "population": 7435,
    "latitude": 45.8159,
    "longitude": 4.8003,
    "altitude": 340,
    "logements": 3304,
    "logementsMaison": 67,
    "prixM2Moyen": 6150,
    "menuisiersRGE": 4,
    "tauxRenovation": "2.8",
    "intercommunalite": "Métropole de Lyon",
    "canton": "Canton de Saint-Didier-au-Mont-d'Or",
    "distanceLyon": 6.4,
    "windExposure": "Modéré (Protégé par les collines ou en fond de vallée)",
    "secteurSauvegarde": true,
    "profilCommune": "commune résidentielle prisée des Monts d'Or",
    "marcheImmobilier": "très haut de gamme (Lyon centre, Monts d'Or)",
    "tauxMaisonLabel": "principalement composé de maisons individuelles et pavillons"
  },
  {
    "nom": "Sathonay-Camp",
    "slug": "sathonay-camp",
    "codeInsee": "69292",
    "codePostal": "69580",
    "population": 7019,
    "latitude": 45.8255,
    "longitude": 4.8792,
    "altitude": 161,
    "logements": 3120,
    "logementsMaison": 60,
    "prixM2Moyen": 3270,
    "menuisiersRGE": 3,
    "tauxRenovation": "2.6",
    "intercommunalite": "Communauté de Communes des Monts du Lyonnais",
    "canton": "Canton de Sathonay-Camp",
    "distanceLyon": 7.6,
    "windExposure": "Modéré (Protégé par les collines ou en fond de vallée)",
    "secteurSauvegarde": false,
    "profilCommune": "bourg rhodanien ou beaujolais typique",
    "marcheImmobilier": "intermédiaire et stable",
    "tauxMaisonLabel": "principalement composé de maisons individuelles et pavillons"
  },
  {
    "nom": "Saint-Bonnet-de-Mure",
    "slug": "saint-bonnet-de-mure",
    "codeInsee": "69287",
    "codePostal": "69720",
    "population": 6984,
    "latitude": 45.6975,
    "longitude": 5.0241,
    "altitude": 152,
    "logements": 3104,
    "logementsMaison": 63,
    "prixM2Moyen": 3520,
    "menuisiersRGE": 2,
    "tauxRenovation": "2.9",
    "intercommunalite": "Communauté de Communes de l'Est Lyonnais",
    "canton": "Canton de Saint-Bonnet-de-Mure",
    "distanceLyon": 16.4,
    "windExposure": "Modéré (Plaine de l'Est Lyonnais)",
    "secteurSauvegarde": false,
    "profilCommune": "bourg rhodanien ou beaujolais typique",
    "marcheImmobilier": "intermédiaire et stable",
    "tauxMaisonLabel": "principalement composé de maisons individuelles et pavillons"
  },
  {
    "nom": "Fontaines-sur-Saône",
    "slug": "fontaines-sur-saone",
    "codeInsee": "69088",
    "codePostal": "69270",
    "population": 6957,
    "latitude": 45.8268,
    "longitude": 4.8537,
    "altitude": 150,
    "logements": 3092,
    "logementsMaison": 70,
    "prixM2Moyen": 3370,
    "menuisiersRGE": 3,
    "tauxRenovation": "2.5",
    "intercommunalite": "Métropole de Lyon",
    "canton": "Canton de Fontaines-sur-Saône",
    "distanceLyon": 7.1,
    "windExposure": "Modéré (Protégé par les collines ou en fond de vallée)",
    "secteurSauvegarde": false,
    "profilCommune": "bourg rhodanien ou beaujolais typique",
    "marcheImmobilier": "intermédiaire et stable",
    "tauxMaisonLabel": "principalement composé de maisons individuelles et pavillons"
  },
  {
    "nom": "Brindas",
    "slug": "brindas",
    "codeInsee": "69028",
    "codePostal": "69126",
    "population": 6775,
    "latitude": 45.7183,
    "longitude": 4.703,
    "altitude": 195,
    "logements": 3011,
    "logementsMaison": 64,
    "prixM2Moyen": 3510,
    "menuisiersRGE": 2,
    "tauxRenovation": "2.6",
    "intercommunalite": "Communauté de Communes des Vallons du Lyonnais",
    "canton": "Canton de Brindas",
    "distanceLyon": 11.5,
    "windExposure": "Modéré (Protégé par les collines ou en fond de vallée)",
    "secteurSauvegarde": false,
    "profilCommune": "bourg rhodanien ou beaujolais typique",
    "marcheImmobilier": "intermédiaire et stable",
    "tauxMaisonLabel": "principalement composé de maisons individuelles et pavillons"
  },
  {
    "nom": "Lentilly",
    "slug": "lentilly",
    "codeInsee": "69112",
    "codePostal": "69210",
    "population": 6623,
    "latitude": 45.8166,
    "longitude": 4.6691,
    "altitude": 269,
    "logements": 2944,
    "logementsMaison": 60,
    "prixM2Moyen": 3400,
    "menuisiersRGE": 3,
    "tauxRenovation": "2.8",
    "intercommunalite": "Communauté de Communes du Pays de L'Arbresle",
    "canton": "Canton de Lentilly",
    "distanceLyon": 14.2,
    "windExposure": "Élevé (Monts du Lyonnais et coteaux exposés)",
    "secteurSauvegarde": false,
    "profilCommune": "bourg rhodanien ou beaujolais typique",
    "marcheImmobilier": "intermédiaire et stable",
    "tauxMaisonLabel": "principalement composé de maisons individuelles et pavillons"
  },
  {
    "nom": "L'Arbresle",
    "slug": "l-arbresle",
    "codeInsee": "69010",
    "codePostal": "69210",
    "population": 6537,
    "latitude": 45.8347,
    "longitude": 4.6102,
    "altitude": 230,
    "logements": 2905,
    "logementsMaison": 62,
    "prixM2Moyen": 3270,
    "menuisiersRGE": 3,
    "tauxRenovation": "2.2",
    "intercommunalite": "Communauté de Communes du Pays de L'Arbresle",
    "canton": "Canton de L'Arbresle",
    "distanceLyon": 19.2,
    "windExposure": "Élevé (Monts du Lyonnais et coteaux exposés)",
    "secteurSauvegarde": false,
    "profilCommune": "bourg rhodanien ou beaujolais typique",
    "marcheImmobilier": "intermédiaire et stable",
    "tauxMaisonLabel": "principalement composé de maisons individuelles et pavillons"
  },
  {
    "nom": "La Mulatière",
    "slug": "la-mulatiere",
    "codeInsee": "69142",
    "codePostal": "69350",
    "population": 6534,
    "latitude": 45.7338,
    "longitude": 4.8118,
    "altitude": 250,
    "logements": 2904,
    "logementsMaison": 21,
    "prixM2Moyen": 3560,
    "menuisiersRGE": 4,
    "tauxRenovation": "2.9",
    "intercommunalite": "Métropole de Lyon",
    "canton": "Canton de La Mulatière",
    "distanceLyon": 3.8,
    "windExposure": "Modéré (Protégé par les collines ou en fond de vallée)",
    "secteurSauvegarde": false,
    "profilCommune": "bourg rhodanien ou beaujolais typique",
    "marcheImmobilier": "intermédiaire et stable",
    "tauxMaisonLabel": "majoritairement collectif avec résidences et immeubles récents"
  },
  {
    "nom": "Grézieu-la-Varenne",
    "slug": "grezieu-la-varenne",
    "codeInsee": "69094",
    "codePostal": "69290",
    "population": 6472,
    "latitude": 45.7469,
    "longitude": 4.6799,
    "altitude": 211,
    "logements": 2876,
    "logementsMaison": 68,
    "prixM2Moyen": 3320,
    "menuisiersRGE": 4,
    "tauxRenovation": "2.9",
    "intercommunalite": "Communauté de Communes des Vallons du Lyonnais",
    "canton": "Canton de Grézieu-la-Varenne",
    "distanceLyon": 12.2,
    "windExposure": "Élevé (Monts du Lyonnais et coteaux exposés)",
    "secteurSauvegarde": false,
    "profilCommune": "bourg rhodanien ou beaujolais typique",
    "marcheImmobilier": "intermédiaire et stable",
    "tauxMaisonLabel": "principalement composé de maisons individuelles et pavillons"
  },
  {
    "nom": "Saint-Cyr-au-Mont-d'Or",
    "slug": "saint-cyr-au-mont-d-or",
    "codeInsee": "69191",
    "codePostal": "69450",
    "population": 6327,
    "latitude": 45.8216,
    "longitude": 4.8162,
    "altitude": 320,
    "logements": 2812,
    "logementsMaison": 66,
    "prixM2Moyen": 6690,
    "menuisiersRGE": 3,
    "tauxRenovation": "2.8",
    "intercommunalite": "Métropole de Lyon",
    "canton": "Canton de Saint-Cyr-au-Mont-d'Or",
    "distanceLyon": 6.6,
    "windExposure": "Modéré (Protégé par les collines ou en fond de vallée)",
    "secteurSauvegarde": true,
    "profilCommune": "commune résidentielle prisée des Monts d'Or",
    "marcheImmobilier": "très haut de gamme (Lyon centre, Monts d'Or)",
    "tauxMaisonLabel": "principalement composé de maisons individuelles et pavillons"
  },
  {
    "nom": "Champagne-au-Mont-d'Or",
    "slug": "champagne-au-mont-d-or",
    "codeInsee": "69040",
    "codePostal": "69410",
    "population": 6311,
    "latitude": 45.8006,
    "longitude": 4.7864,
    "altitude": 301,
    "logements": 2805,
    "logementsMaison": 88,
    "prixM2Moyen": 3290,
    "menuisiersRGE": 3,
    "tauxRenovation": "2.8",
    "intercommunalite": "Communauté de Communes des Monts du Lyonnais",
    "canton": "Canton de Champagne-au-Mont-d'Or",
    "distanceLyon": 5.6,
    "windExposure": "Modéré (Protégé par les collines ou en fond de vallée)",
    "secteurSauvegarde": true,
    "profilCommune": "bourg rhodanien ou beaujolais typique",
    "marcheImmobilier": "intermédiaire et stable",
    "tauxMaisonLabel": "très majoritairement composé de villas contemporaines et maisons de village"
  },
  {
    "nom": "Vaugneray",
    "slug": "vaugneray",
    "codeInsee": "69255",
    "codePostal": "69670",
    "population": 6304,
    "latitude": 45.73,
    "longitude": 4.6502,
    "altitude": 166,
    "logements": 2802,
    "logementsMaison": 71,
    "prixM2Moyen": 3190,
    "menuisiersRGE": 4,
    "tauxRenovation": "2.1",
    "intercommunalite": "Communauté de Communes des Vallons du Lyonnais",
    "canton": "Canton de Vaugneray",
    "distanceLyon": 14.9,
    "windExposure": "Élevé (Monts du Lyonnais et coteaux exposés)",
    "secteurSauvegarde": false,
    "profilCommune": "bourg rhodanien ou beaujolais typique",
    "marcheImmobilier": "intermédiaire et stable",
    "tauxMaisonLabel": "principalement composé de maisons individuelles et pavillons"
  },
  {
    "nom": "Mornant",
    "slug": "mornant",
    "codeInsee": "69141",
    "codePostal": "69440",
    "population": 6282,
    "latitude": 45.6162,
    "longitude": 4.6747,
    "altitude": 251,
    "logements": 2792,
    "logementsMaison": 60,
    "prixM2Moyen": 3330,
    "menuisiersRGE": 4,
    "tauxRenovation": "2.1",
    "intercommunalite": "Communauté de Communes des Monts du Lyonnais",
    "canton": "Canton de Mornant",
    "distanceLyon": 20.7,
    "windExposure": "Élevé (Monts du Lyonnais et coteaux exposés)",
    "secteurSauvegarde": false,
    "profilCommune": "bourg rhodanien ou beaujolais typique",
    "marcheImmobilier": "intermédiaire et stable",
    "tauxMaisonLabel": "principalement composé de maisons individuelles et pavillons"
  },
  {
    "nom": "Saint-Symphorien-d'Ozon",
    "slug": "saint-symphorien-d-ozon",
    "codeInsee": "69291",
    "codePostal": "69360",
    "population": 6186,
    "latitude": 45.6386,
    "longitude": 4.8666,
    "altitude": 262,
    "logements": 2749,
    "logementsMaison": 71,
    "prixM2Moyen": 3470,
    "menuisiersRGE": 3,
    "tauxRenovation": "2.2",
    "intercommunalite": "Communauté de Communes du Pays de l'Ozon",
    "canton": "Canton de Saint-Symphorien-d'Ozon",
    "distanceLyon": 14.2,
    "windExposure": "Modéré (Protégé par les collines ou en fond de vallée)",
    "secteurSauvegarde": false,
    "profilCommune": "bourg rhodanien ou beaujolais typique",
    "marcheImmobilier": "intermédiaire et stable",
    "tauxMaisonLabel": "principalement composé de maisons individuelles et pavillons"
  },
  {
    "nom": "Jonage",
    "slug": "jonage",
    "codeInsee": "69279",
    "codePostal": "69330",
    "population": 6144,
    "latitude": 45.7886,
    "longitude": 5.0377,
    "altitude": 256,
    "logements": 2731,
    "logementsMaison": 65,
    "prixM2Moyen": 3460,
    "menuisiersRGE": 4,
    "tauxRenovation": "2.1",
    "intercommunalite": "Métropole de Lyon",
    "canton": "Canton de Jonage",
    "distanceLyon": 15.9,
    "windExposure": "Modéré (Plaine de l'Est Lyonnais)",
    "secteurSauvegarde": false,
    "profilCommune": "bourg rhodanien ou beaujolais typique",
    "marcheImmobilier": "intermédiaire et stable",
    "tauxMaisonLabel": "principalement composé de maisons individuelles et pavillons"
  },
  {
    "nom": "Saint-Laurent-de-Mure",
    "slug": "saint-laurent-de-mure",
    "codeInsee": "69288",
    "codePostal": "69720",
    "population": 5791,
    "latitude": 45.6842,
    "longitude": 5.0597,
    "altitude": 151,
    "logements": 2574,
    "logementsMaison": 62,
    "prixM2Moyen": 3470,
    "menuisiersRGE": 3,
    "tauxRenovation": "2.4",
    "intercommunalite": "Communauté de Communes de l'Est Lyonnais",
    "canton": "Canton de Saint-Laurent-de-Mure",
    "distanceLyon": 19.5,
    "windExposure": "Modéré (Plaine de l'Est Lyonnais)",
    "secteurSauvegarde": false,
    "profilCommune": "bourg rhodanien ou beaujolais typique",
    "marcheImmobilier": "intermédiaire et stable",
    "tauxMaisonLabel": "principalement composé de maisons individuelles et pavillons"
  },
  {
    "nom": "Thizy-les-Bourgs",
    "slug": "thizy-les-bourgs",
    "codeInsee": "69248",
    "codePostal": "69240",
    "population": 5771,
    "latitude": 46.0505,
    "longitude": 4.3109,
    "altitude": 204,
    "logements": 2565,
    "logementsMaison": 67,
    "prixM2Moyen": 3530,
    "menuisiersRGE": 4,
    "tauxRenovation": "2.2",
    "intercommunalite": "Communauté de Communes des Monts du Lyonnais",
    "canton": "Canton de Thizy-les-Bourgs",
    "distanceLyon": 51.6,
    "windExposure": "Élevé (Monts du Lyonnais et coteaux exposés)",
    "secteurSauvegarde": false,
    "profilCommune": "bourg rhodanien ou beaujolais typique",
    "marcheImmobilier": "intermédiaire et stable",
    "tauxMaisonLabel": "principalement composé de maisons individuelles et pavillons"
  },
  {
    "nom": "Ternay",
    "slug": "ternay",
    "codeInsee": "69297",
    "codePostal": "69360",
    "population": 5596,
    "latitude": 45.6083,
    "longitude": 4.803,
    "altitude": 165,
    "logements": 2487,
    "logementsMaison": 70,
    "prixM2Moyen": 3170,
    "menuisiersRGE": 3,
    "tauxRenovation": "2.6",
    "intercommunalite": "Communauté de Communes du Pays de l'Ozon",
    "canton": "Canton de Ternay",
    "distanceLyon": 17.5,
    "windExposure": "Modéré (Protégé par les collines ou en fond de vallée)",
    "secteurSauvegarde": false,
    "profilCommune": "bourg rhodanien ou beaujolais typique",
    "marcheImmobilier": "intermédiaire et stable",
    "tauxMaisonLabel": "principalement composé de maisons individuelles et pavillons"
  },
  {
    "nom": "Genay",
    "slug": "genay",
    "codeInsee": "69278",
    "codePostal": "69730",
    "population": 5585,
    "latitude": 45.8989,
    "longitude": 4.8389,
    "altitude": 150,
    "logements": 2482,
    "logementsMaison": 67,
    "prixM2Moyen": 3260,
    "menuisiersRGE": 4,
    "tauxRenovation": "2.5",
    "intercommunalite": "Métropole de Lyon",
    "canton": "Canton de Genay",
    "distanceLyon": 15,
    "windExposure": "Modéré (Protégé par les collines ou en fond de vallée)",
    "secteurSauvegarde": false,
    "profilCommune": "bourg rhodanien ou beaujolais typique",
    "marcheImmobilier": "intermédiaire et stable",
    "tauxMaisonLabel": "principalement composé de maisons individuelles et pavillons"
  },
  {
    "nom": "Saint-Genis-les-Ollières",
    "slug": "saint-genis-les-ollieres",
    "codeInsee": "69205",
    "codePostal": "69290",
    "population": 5439,
    "latitude": 45.7614,
    "longitude": 4.7248,
    "altitude": 247,
    "logements": 2417,
    "logementsMaison": 68,
    "prixM2Moyen": 3270,
    "menuisiersRGE": 2,
    "tauxRenovation": "2.1",
    "intercommunalite": "Communauté de Communes des Vallons du Lyonnais",
    "canton": "Canton de Saint-Genis-les-Ollières",
    "distanceLyon": 8.6,
    "windExposure": "Modéré (Protégé par les collines ou en fond de vallée)",
    "secteurSauvegarde": false,
    "profilCommune": "bourg rhodanien ou beaujolais typique",
    "marcheImmobilier": "intermédiaire et stable",
    "tauxMaisonLabel": "principalement composé de maisons individuelles et pavillons"
  },
  {
    "nom": "Charbonnières-les-Bains",
    "slug": "charbonnieres-les-bains",
    "codeInsee": "69044",
    "codePostal": "69260",
    "population": 5383,
    "latitude": 45.7792,
    "longitude": 4.743,
    "altitude": 150,
    "logements": 2392,
    "logementsMaison": 67,
    "prixM2Moyen": 6360,
    "menuisiersRGE": 4,
    "tauxRenovation": "2.1",
    "intercommunalite": "Communauté de Communes des Monts du Lyonnais",
    "canton": "Canton de Charbonnières-les-Bains",
    "distanceLyon": 7.4,
    "windExposure": "Modéré (Protégé par les collines ou en fond de vallée)",
    "secteurSauvegarde": false,
    "profilCommune": "bourg rhodanien ou beaujolais typique",
    "marcheImmobilier": "très haut de gamme (Lyon centre, Monts d'Or)",
    "tauxMaisonLabel": "principalement composé de maisons individuelles et pavillons"
  },
  {
    "nom": "Vindry-sur-Turdine",
    "slug": "vindry-sur-turdine",
    "codeInsee": "69157",
    "codePostal": "69490",
    "population": 5305,
    "latitude": 45.8886,
    "longitude": 4.4948,
    "altitude": 257,
    "logements": 2358,
    "logementsMaison": 60,
    "prixM2Moyen": 3280,
    "menuisiersRGE": 3,
    "tauxRenovation": "2.5",
    "intercommunalite": "Communauté de Communes des Monts du Lyonnais",
    "canton": "Canton de Vindry-sur-Turdine",
    "distanceLyon": 29.8,
    "windExposure": "Élevé (Monts du Lyonnais et coteaux exposés)",
    "secteurSauvegarde": false,
    "profilCommune": "bourg rhodanien ou beaujolais typique",
    "marcheImmobilier": "intermédiaire et stable",
    "tauxMaisonLabel": "principalement composé de maisons individuelles et pavillons"
  },
  {
    "nom": "Vernaison",
    "slug": "vernaison",
    "codeInsee": "69260",
    "codePostal": "69390",
    "population": 5210,
    "latitude": 45.6464,
    "longitude": 4.8121,
    "altitude": 233,
    "logements": 2316,
    "logementsMaison": 66,
    "prixM2Moyen": 3360,
    "menuisiersRGE": 2,
    "tauxRenovation": "2.3",
    "intercommunalite": "Métropole de Lyon",
    "canton": "Canton de Vernaison",
    "distanceLyon": 13.2,
    "windExposure": "Modéré (Protégé par les collines ou en fond de vallée)",
    "secteurSauvegarde": false,
    "profilCommune": "bourg rhodanien ou beaujolais typique",
    "marcheImmobilier": "intermédiaire et stable",
    "tauxMaisonLabel": "principalement composé de maisons individuelles et pavillons"
  },
  {
    "nom": "Amplepuis",
    "slug": "amplepuis",
    "codeInsee": "69006",
    "codePostal": "69550",
    "population": 4876,
    "latitude": 45.966,
    "longitude": 4.317,
    "altitude": 262,
    "logements": 2167,
    "logementsMaison": 71,
    "prixM2Moyen": 3310,
    "menuisiersRGE": 4,
    "tauxRenovation": "2.4",
    "intercommunalite": "Communauté de Communes des Monts du Lyonnais",
    "canton": "Canton de Amplepuis",
    "distanceLyon": 46,
    "windExposure": "Élevé (Monts du Lyonnais et coteaux exposés)",
    "secteurSauvegarde": false,
    "profilCommune": "bourg rhodanien ou beaujolais typique",
    "marcheImmobilier": "intermédiaire et stable",
    "tauxMaisonLabel": "principalement composé de maisons individuelles et pavillons"
  },
  {
    "nom": "Charly",
    "slug": "charly",
    "codeInsee": "69046",
    "codePostal": "69390",
    "population": 4811,
    "latitude": 45.6527,
    "longitude": 4.7871,
    "altitude": 181,
    "logements": 2138,
    "logementsMaison": 68,
    "prixM2Moyen": 3430,
    "menuisiersRGE": 4,
    "tauxRenovation": "2.4",
    "intercommunalite": "Communauté de Communes des Monts du Lyonnais",
    "canton": "Canton de Charly",
    "distanceLyon": 12.9,
    "windExposure": "Modéré (Protégé par les collines ou en fond de vallée)",
    "secteurSauvegarde": false,
    "profilCommune": "bourg rhodanien ou beaujolais typique",
    "marcheImmobilier": "intermédiaire et stable",
    "tauxMaisonLabel": "principalement composé de maisons individuelles et pavillons"
  },
  {
    "nom": "Limas",
    "slug": "limas",
    "codeInsee": "69115",
    "codePostal": "69400",
    "population": 4750,
    "latitude": 45.9717,
    "longitude": 4.7196,
    "altitude": 150,
    "logements": 2111,
    "logementsMaison": 69,
    "prixM2Moyen": 3560,
    "menuisiersRGE": 2,
    "tauxRenovation": "2.7",
    "intercommunalite": "Communauté d'Agglomération de Villefranche Beaujolais Saône",
    "canton": "Villefranche-sur-Saône",
    "distanceLyon": 24.8,
    "windExposure": "Modéré (Protégé par les collines ou en fond de vallée)",
    "secteurSauvegarde": false,
    "profilCommune": "bourg rhodanien ou beaujolais typique",
    "marcheImmobilier": "intermédiaire et stable",
    "tauxMaisonLabel": "principalement composé de maisons individuelles et pavillons"
  },
  {
    "nom": "Saint-Georges-de-Reneins",
    "slug": "saint-georges-de-reneins",
    "codeInsee": "69206",
    "codePostal": "69830",
    "population": 4677,
    "latitude": 46.0587,
    "longitude": 4.7164,
    "altitude": 150,
    "logements": 2079,
    "logementsMaison": 66,
    "prixM2Moyen": 3520,
    "menuisiersRGE": 4,
    "tauxRenovation": "2.9",
    "intercommunalite": "Communauté de Communes des Monts du Lyonnais",
    "canton": "Canton de Saint-Georges-de-Reneins",
    "distanceLyon": 34,
    "windExposure": "Modéré (Protégé par les collines ou en fond de vallée)",
    "secteurSauvegarde": false,
    "profilCommune": "bourg rhodanien ou beaujolais typique",
    "marcheImmobilier": "intermédiaire et stable",
    "tauxMaisonLabel": "principalement composé de maisons individuelles et pavillons"
  },
  {
    "nom": "Collonges-au-Mont-d'Or",
    "slug": "collonges-au-mont-d-or",
    "codeInsee": "69063",
    "codePostal": "69660",
    "population": 4669,
    "latitude": 45.8188,
    "longitude": 4.8425,
    "altitude": 385,
    "logements": 2075,
    "logementsMaison": 82,
    "prixM2Moyen": 3240,
    "menuisiersRGE": 3,
    "tauxRenovation": "2.2",
    "intercommunalite": "Communauté de Communes des Monts du Lyonnais",
    "canton": "Canton de Collonges-au-Mont-d'Or",
    "distanceLyon": 6.1,
    "windExposure": "Modéré (Protégé par les collines ou en fond de vallée)",
    "secteurSauvegarde": true,
    "profilCommune": "bourg rhodanien ou beaujolais typique",
    "marcheImmobilier": "intermédiaire et stable",
    "tauxMaisonLabel": "très majoritairement composé de villas contemporaines et maisons de village"
  },
  {
    "nom": "Soucieu-en-Jarrest",
    "slug": "soucieu-en-jarrest",
    "codeInsee": "69176",
    "codePostal": "69510",
    "population": 4660,
    "latitude": 45.677,
    "longitude": 4.6907,
    "altitude": 191,
    "logements": 2071,
    "logementsMaison": 66,
    "prixM2Moyen": 3420,
    "menuisiersRGE": 2,
    "tauxRenovation": "2.1",
    "intercommunalite": "Communauté de Communes des Monts du Lyonnais",
    "canton": "Canton de Soucieu-en-Jarrest",
    "distanceLyon": 14.8,
    "windExposure": "Élevé (Monts du Lyonnais et coteaux exposés)",
    "secteurSauvegarde": false,
    "profilCommune": "bourg rhodanien ou beaujolais typique",
    "marcheImmobilier": "intermédiaire et stable",
    "tauxMaisonLabel": "principalement composé de maisons individuelles et pavillons"
  },
  {
    "nom": "La Tour-de-Salvagny",
    "slug": "la-tour-de-salvagny",
    "codeInsee": "69250",
    "codePostal": "69890",
    "population": 4649,
    "latitude": 45.8086,
    "longitude": 4.7129,
    "altitude": 198,
    "logements": 2066,
    "logementsMaison": 61,
    "prixM2Moyen": 3400,
    "menuisiersRGE": 3,
    "tauxRenovation": "2.2",
    "intercommunalite": "Communauté de Communes des Monts du Lyonnais",
    "canton": "Canton de La Tour-de-Salvagny",
    "distanceLyon": 10.7,
    "windExposure": "Modéré (Protégé par les collines ou en fond de vallée)",
    "secteurSauvegarde": false,
    "profilCommune": "bourg rhodanien ou beaujolais typique",
    "marcheImmobilier": "intermédiaire et stable",
    "tauxMaisonLabel": "principalement composé de maisons individuelles et pavillons"
  },
  {
    "nom": "Saint-Pierre-de-Chandieu",
    "slug": "saint-pierre-de-chandieu",
    "codeInsee": "69289",
    "codePostal": "69780",
    "population": 4616,
    "latitude": 45.6471,
    "longitude": 5.0085,
    "altitude": 150,
    "logements": 2052,
    "logementsMaison": 60,
    "prixM2Moyen": 3450,
    "menuisiersRGE": 3,
    "tauxRenovation": "2.5",
    "intercommunalite": "Communauté de Communes des Monts du Lyonnais",
    "canton": "Canton de Saint-Pierre-de-Chandieu",
    "distanceLyon": 18.7,
    "windExposure": "Modéré (Plaine de l'Est Lyonnais)",
    "secteurSauvegarde": false,
    "profilCommune": "bourg rhodanien ou beaujolais typique",
    "marcheImmobilier": "intermédiaire et stable",
    "tauxMaisonLabel": "principalement composé de maisons individuelles et pavillons"
  },
  {
    "nom": "Arnas",
    "slug": "arnas",
    "codeInsee": "69013",
    "codePostal": "69400",
    "population": 4601,
    "latitude": 46.0194,
    "longitude": 4.7102,
    "altitude": 150,
    "logements": 2045,
    "logementsMaison": 62,
    "prixM2Moyen": 3410,
    "menuisiersRGE": 3,
    "tauxRenovation": "2.6",
    "intercommunalite": "Communauté d'Agglomération de Villefranche Beaujolais Saône",
    "canton": "Villefranche-sur-Saône",
    "distanceLyon": 30,
    "windExposure": "Modéré (Protégé par les collines ou en fond de vallée)",
    "secteurSauvegarde": false,
    "profilCommune": "bourg rhodanien ou beaujolais typique",
    "marcheImmobilier": "intermédiaire et stable",
    "tauxMaisonLabel": "principalement composé de maisons individuelles et pavillons"
  },
  {
    "nom": "Chaponnay",
    "slug": "chaponnay",
    "codeInsee": "69270",
    "codePostal": "69970",
    "population": 4548,
    "latitude": 45.6315,
    "longitude": 4.9584,
    "altitude": 185,
    "logements": 2021,
    "logementsMaison": 66,
    "prixM2Moyen": 3590,
    "menuisiersRGE": 2,
    "tauxRenovation": "2.2",
    "intercommunalite": "Communauté de Communes des Monts du Lyonnais",
    "canton": "Canton de Chaponnay",
    "distanceLyon": 17.6,
    "windExposure": "Modéré (Plaine de l'Est Lyonnais)",
    "secteurSauvegarde": false,
    "profilCommune": "bourg rhodanien ou beaujolais typique",
    "marcheImmobilier": "intermédiaire et stable",
    "tauxMaisonLabel": "principalement composé de maisons individuelles et pavillons"
  },
  {
    "nom": "Communay",
    "slug": "communay",
    "codeInsee": "69272",
    "codePostal": "69360",
    "population": 4540,
    "latitude": 45.5977,
    "longitude": 4.8359,
    "altitude": 215,
    "logements": 2018,
    "logementsMaison": 66,
    "prixM2Moyen": 3460,
    "menuisiersRGE": 2,
    "tauxRenovation": "2.4",
    "intercommunalite": "Communauté de Communes du Pays de l'Ozon",
    "canton": "Canton de Communay",
    "distanceLyon": 18.5,
    "windExposure": "Modéré (Protégé par les collines ou en fond de vallée)",
    "secteurSauvegarde": false,
    "profilCommune": "bourg rhodanien ou beaujolais typique",
    "marcheImmobilier": "intermédiaire et stable",
    "tauxMaisonLabel": "principalement composé de maisons individuelles et pavillons"
  },
  {
    "nom": "Chazay-d'Azergues",
    "slug": "chazay-d-azergues",
    "codeInsee": "69052",
    "codePostal": "69380",
    "population": 4410,
    "latitude": 45.8743,
    "longitude": 4.71,
    "altitude": 232,
    "logements": 1960,
    "logementsMaison": 65,
    "prixM2Moyen": 3450,
    "menuisiersRGE": 4,
    "tauxRenovation": "2.5",
    "intercommunalite": "Communauté de Communes des Monts du Lyonnais",
    "canton": "Canton de Chazay-d'Azergues",
    "distanceLyon": 15.7,
    "windExposure": "Modéré (Protégé par les collines ou en fond de vallée)",
    "secteurSauvegarde": false,
    "profilCommune": "bourg rhodanien ou beaujolais typique",
    "marcheImmobilier": "intermédiaire et stable",
    "tauxMaisonLabel": "principalement composé de maisons individuelles et pavillons"
  },
  {
    "nom": "Chabanière",
    "slug": "chabaniere",
    "codeInsee": "69228",
    "codePostal": "69440",
    "population": 4323,
    "latitude": 45.5853,
    "longitude": 4.6187,
    "altitude": 150,
    "logements": 1921,
    "logementsMaison": 67,
    "prixM2Moyen": 3210,
    "menuisiersRGE": 3,
    "tauxRenovation": "2.2",
    "intercommunalite": "Communauté de Communes des Monts du Lyonnais",
    "canton": "Canton de Chabanière",
    "distanceLyon": 26.1,
    "windExposure": "Élevé (Monts du Lyonnais et coteaux exposés)",
    "secteurSauvegarde": false,
    "profilCommune": "bourg rhodanien ou beaujolais typique",
    "marcheImmobilier": "intermédiaire et stable",
    "tauxMaisonLabel": "principalement composé de maisons individuelles et pavillons"
  },
  {
    "nom": "Cours",
    "slug": "cours",
    "codeInsee": "69066",
    "codePostal": "69470",
    "population": 4306,
    "latitude": 46.0968,
    "longitude": 4.3445,
    "altitude": 162,
    "logements": 1914,
    "logementsMaison": 61,
    "prixM2Moyen": 3330,
    "menuisiersRGE": 4,
    "tauxRenovation": "2.2",
    "intercommunalite": "Communauté de Communes des Monts du Lyonnais",
    "canton": "Canton de Cours",
    "distanceLyon": 53,
    "windExposure": "Élevé (Monts du Lyonnais et coteaux exposés)",
    "secteurSauvegarde": false,
    "profilCommune": "bourg rhodanien ou beaujolais typique",
    "marcheImmobilier": "intermédiaire et stable",
    "tauxMaisonLabel": "principalement composé de maisons individuelles et pavillons"
  },
  {
    "nom": "Millery",
    "slug": "millery",
    "codeInsee": "69133",
    "codePostal": "69390",
    "population": 4299,
    "latitude": 45.6307,
    "longitude": 4.781,
    "altitude": 160,
    "logements": 1911,
    "logementsMaison": 71,
    "prixM2Moyen": 3470,
    "menuisiersRGE": 3,
    "tauxRenovation": "2.2",
    "intercommunalite": "Communauté de Communes de la Vallée du Garon",
    "canton": "Canton de Millery",
    "distanceLyon": 15.4,
    "windExposure": "Modéré (Protégé par les collines ou en fond de vallée)",
    "secteurSauvegarde": false,
    "profilCommune": "bourg rhodanien ou beaujolais typique",
    "marcheImmobilier": "intermédiaire et stable",
    "tauxMaisonLabel": "principalement composé de maisons individuelles et pavillons"
  },
  {
    "nom": "Beauvallon",
    "slug": "beauvallon",
    "codeInsee": "69179",
    "codePostal": "69700",
    "population": 4260,
    "latitude": 45.5898,
    "longitude": 4.7041,
    "altitude": 229,
    "logements": 1893,
    "logementsMaison": 62,
    "prixM2Moyen": 3480,
    "menuisiersRGE": 4,
    "tauxRenovation": "2.6",
    "intercommunalite": "Communauté de Communes des Monts du Lyonnais",
    "canton": "Canton de Beauvallon",
    "distanceLyon": 21.9,
    "windExposure": "Modéré (Protégé par les collines ou en fond de vallée)",
    "secteurSauvegarde": false,
    "profilCommune": "bourg rhodanien ou beaujolais typique",
    "marcheImmobilier": "intermédiaire et stable",
    "tauxMaisonLabel": "principalement composé de maisons individuelles et pavillons"
  },
  {
    "nom": "Porte des Pierres Dorées",
    "slug": "porte-des-pierres-dorees",
    "codeInsee": "69114",
    "codePostal": "69400",
    "population": 4185,
    "latitude": 45.9628,
    "longitude": 4.6509,
    "altitude": 150,
    "logements": 1860,
    "logementsMaison": 64,
    "prixM2Moyen": 3570,
    "menuisiersRGE": 4,
    "tauxRenovation": "2.6",
    "intercommunalite": "Communauté d'Agglomération de Villefranche Beaujolais Saône",
    "canton": "Villefranche-sur-Saône",
    "distanceLyon": 26.3,
    "windExposure": "Élevé (Monts du Lyonnais et coteaux exposés)",
    "secteurSauvegarde": false,
    "profilCommune": "bourg rhodanien ou beaujolais typique",
    "marcheImmobilier": "intermédiaire et stable",
    "tauxMaisonLabel": "principalement composé de maisons individuelles et pavillons"
  },
  {
    "nom": "Pusignan",
    "slug": "pusignan",
    "codeInsee": "69285",
    "codePostal": "69330",
    "population": 4119,
    "latitude": 45.7571,
    "longitude": 5.0659,
    "altitude": 187,
    "logements": 1831,
    "logementsMaison": 68,
    "prixM2Moyen": 3130,
    "menuisiersRGE": 4,
    "tauxRenovation": "2.9",
    "intercommunalite": "Communauté de Communes des Monts du Lyonnais",
    "canton": "Canton de Pusignan",
    "distanceLyon": 17.9,
    "windExposure": "Modéré (Plaine de l'Est Lyonnais)",
    "secteurSauvegarde": false,
    "profilCommune": "bourg rhodanien ou beaujolais typique",
    "marcheImmobilier": "intermédiaire et stable",
    "tauxMaisonLabel": "principalement composé de maisons individuelles et pavillons"
  },
  {
    "nom": "Val d'Oingt",
    "slug": "val-d-oingt",
    "codeInsee": "69024",
    "codePostal": "69620",
    "population": 4117,
    "latitude": 45.9386,
    "longitude": 4.5668,
    "altitude": 240,
    "logements": 1830,
    "logementsMaison": 61,
    "prixM2Moyen": 3470,
    "menuisiersRGE": 3,
    "tauxRenovation": "2.6",
    "intercommunalite": "Communauté de Communes Beaujolais Pierres Dorées",
    "canton": "Canton de Val d'Oingt",
    "distanceLyon": 28.5,
    "windExposure": "Élevé (Monts du Lyonnais et coteaux exposés)",
    "secteurSauvegarde": false,
    "profilCommune": "bourg rhodanien ou beaujolais typique",
    "marcheImmobilier": "intermédiaire et stable",
    "tauxMaisonLabel": "principalement composé de maisons individuelles et pavillons"
  },
  {
    "nom": "Limonest",
    "slug": "limonest",
    "codeInsee": "69116",
    "codePostal": "69760",
    "population": 4012,
    "latitude": 45.8267,
    "longitude": 4.7682,
    "altitude": 269,
    "logements": 1783,
    "logementsMaison": 69,
    "prixM2Moyen": 6470,
    "menuisiersRGE": 3,
    "tauxRenovation": "2.2",
    "intercommunalite": "Métropole de Lyon",
    "canton": "Canton de Limonest",
    "distanceLyon": 8.7,
    "windExposure": "Modéré (Protégé par les collines ou en fond de vallée)",
    "secteurSauvegarde": false,
    "profilCommune": "commune résidentielle prisée des Monts d'Or",
    "marcheImmobilier": "très haut de gamme (Lyon centre, Monts d'Or)",
    "tauxMaisonLabel": "principalement composé de maisons individuelles et pavillons"
  },
  {
    "nom": "Condrieu",
    "slug": "condrieu",
    "codeInsee": "69064",
    "codePostal": "69420",
    "population": 3957,
    "latitude": 45.4748,
    "longitude": 4.7516,
    "altitude": 261,
    "logements": 1759,
    "logementsMaison": 70,
    "prixM2Moyen": 3370,
    "menuisiersRGE": 4,
    "tauxRenovation": "2.3",
    "intercommunalite": "Communauté de Communes des Monts du Lyonnais",
    "canton": "Canton de Condrieu",
    "distanceLyon": 32.8,
    "windExposure": "Modéré (Protégé par les collines ou en fond de vallée)",
    "secteurSauvegarde": false,
    "profilCommune": "commune ou village résidentiel du Rhône",
    "marcheImmobilier": "intermédiaire et stable",
    "tauxMaisonLabel": "principalement composé de maisons individuelles et pavillons"
  },
  {
    "nom": "Saint-Martin-en-Haut",
    "slug": "saint-martin-en-haut",
    "codeInsee": "69227",
    "codePostal": "69850",
    "population": 3942,
    "latitude": 45.6583,
    "longitude": 4.5561,
    "altitude": 178,
    "logements": 1752,
    "logementsMaison": 71,
    "prixM2Moyen": 3340,
    "menuisiersRGE": 3,
    "tauxRenovation": "2.5",
    "intercommunalite": "Communauté de Communes des Monts du Lyonnais",
    "canton": "Canton de Saint-Martin-en-Haut",
    "distanceLyon": 24.7,
    "windExposure": "Élevé (Monts du Lyonnais et coteaux exposés)",
    "secteurSauvegarde": false,
    "profilCommune": "commune ou village résidentiel du Rhône",
    "marcheImmobilier": "intermédiaire et stable",
    "tauxMaisonLabel": "principalement composé de maisons individuelles et pavillons"
  },
  {
    "nom": "Saint-Symphorien-sur-Coise",
    "slug": "saint-symphorien-sur-coise",
    "codeInsee": "69238",
    "codePostal": "69590",
    "population": 3785,
    "latitude": 45.6314,
    "longitude": 4.4456,
    "altitude": 171,
    "logements": 1682,
    "logementsMaison": 70,
    "prixM2Moyen": 3580,
    "menuisiersRGE": 2,
    "tauxRenovation": "2.7",
    "intercommunalite": "Communauté de Communes des Monts du Lyonnais",
    "canton": "Canton de Saint-Symphorien-sur-Coise",
    "distanceLyon": 33.7,
    "windExposure": "Élevé (Monts du Lyonnais et coteaux exposés)",
    "secteurSauvegarde": true,
    "profilCommune": "commune ou village résidentiel du Rhône",
    "marcheImmobilier": "intermédiaire et stable",
    "tauxMaisonLabel": "principalement composé de maisons individuelles et pavillons"
  },
  {
    "nom": "Marcy-l'Étoile",
    "slug": "marcy-l-etoile",
    "codeInsee": "69127",
    "codePostal": "69280",
    "population": 3778,
    "latitude": 45.7855,
    "longitude": 4.7129,
    "altitude": 218,
    "logements": 1679,
    "logementsMaison": 69,
    "prixM2Moyen": 3480,
    "menuisiersRGE": 3,
    "tauxRenovation": "2.8",
    "intercommunalite": "Communauté de Communes des Monts du Lyonnais",
    "canton": "Canton de Marcy-l'Étoile",
    "distanceLyon": 9.8,
    "windExposure": "Modéré (Protégé par les collines ou en fond de vallée)",
    "secteurSauvegarde": false,
    "profilCommune": "commune ou village résidentiel du Rhône",
    "marcheImmobilier": "intermédiaire et stable",
    "tauxMaisonLabel": "principalement composé de maisons individuelles et pavillons"
  },
  {
    "nom": "Quincieux",
    "slug": "quincieux",
    "codeInsee": "69163",
    "codePostal": "69650",
    "population": 3679,
    "latitude": 45.9168,
    "longitude": 4.7724,
    "altitude": 271,
    "logements": 1635,
    "logementsMaison": 68,
    "prixM2Moyen": 3100,
    "menuisiersRGE": 4,
    "tauxRenovation": "2.7",
    "intercommunalite": "Communauté de Communes des Monts du Lyonnais",
    "canton": "Canton de Quincieux",
    "distanceLyon": 17.7,
    "windExposure": "Modéré (Protégé par les collines ou en fond de vallée)",
    "secteurSauvegarde": false,
    "profilCommune": "commune ou village résidentiel du Rhône",
    "marcheImmobilier": "intermédiaire et stable",
    "tauxMaisonLabel": "principalement composé de maisons individuelles et pavillons"
  },
  {
    "nom": "Messimy",
    "slug": "messimy",
    "codeInsee": "69131",
    "codePostal": "69510",
    "population": 3546,
    "latitude": 45.6978,
    "longitude": 4.6748,
    "altitude": 229,
    "logements": 1576,
    "logementsMaison": 68,
    "prixM2Moyen": 3290,
    "menuisiersRGE": 3,
    "tauxRenovation": "2.5",
    "intercommunalite": "Communauté de Communes des Monts du Lyonnais",
    "canton": "Canton de Messimy",
    "distanceLyon": 14.5,
    "windExposure": "Élevé (Monts du Lyonnais et coteaux exposés)",
    "secteurSauvegarde": false,
    "profilCommune": "commune ou village résidentiel du Rhône",
    "marcheImmobilier": "intermédiaire et stable",
    "tauxMaisonLabel": "principalement composé de maisons individuelles et pavillons"
  },
  {
    "nom": "Thurins",
    "slug": "thurins",
    "codeInsee": "69249",
    "codePostal": "69510",
    "population": 3404,
    "latitude": 45.6809,
    "longitude": 4.6252,
    "altitude": 167,
    "logements": 1513,
    "logementsMaison": 60,
    "prixM2Moyen": 3500,
    "menuisiersRGE": 3,
    "tauxRenovation": "2.8",
    "intercommunalite": "Communauté de Communes des Monts du Lyonnais",
    "canton": "Canton de Thurins",
    "distanceLyon": 18.8,
    "windExposure": "Élevé (Monts du Lyonnais et coteaux exposés)",
    "secteurSauvegarde": false,
    "profilCommune": "commune ou village résidentiel du Rhône",
    "marcheImmobilier": "intermédiaire et stable",
    "tauxMaisonLabel": "principalement composé de maisons individuelles et pavillons"
  },
  {
    "nom": "Vourles",
    "slug": "vourles",
    "codeInsee": "69268",
    "codePostal": "69390",
    "population": 3332,
    "latitude": 45.6569,
    "longitude": 4.7691,
    "altitude": 206,
    "logements": 1481,
    "logementsMaison": 63,
    "prixM2Moyen": 3220,
    "menuisiersRGE": 4,
    "tauxRenovation": "2.7",
    "intercommunalite": "Communauté de Communes de la Vallée du Garon",
    "canton": "Canton de Vourles",
    "distanceLyon": 13,
    "windExposure": "Modéré (Protégé par les collines ou en fond de vallée)",
    "secteurSauvegarde": false,
    "profilCommune": "commune ou village résidentiel du Rhône",
    "marcheImmobilier": "intermédiaire et stable",
    "tauxMaisonLabel": "principalement composé de maisons individuelles et pavillons"
  },
  {
    "nom": "Montanay",
    "slug": "montanay",
    "codeInsee": "69284",
    "codePostal": "69250",
    "population": 3308,
    "latitude": 45.8793,
    "longitude": 4.8657,
    "altitude": 371,
    "logements": 1470,
    "logementsMaison": 76,
    "prixM2Moyen": 3110,
    "menuisiersRGE": 2,
    "tauxRenovation": "2.1",
    "intercommunalite": "Communauté de Communes des Monts du Lyonnais",
    "canton": "Canton de Montanay",
    "distanceLyon": 13,
    "windExposure": "Modéré (Protégé par les collines ou en fond de vallée)",
    "secteurSauvegarde": false,
    "profilCommune": "commune ou village résidentiel du Rhône",
    "marcheImmobilier": "intermédiaire et stable",
    "tauxMaisonLabel": "principalement composé de maisons individuelles et pavillons"
  },
  {
    "nom": "Montagny",
    "slug": "montagny",
    "codeInsee": "69136",
    "codePostal": "69700",
    "population": 3218,
    "latitude": 45.6296,
    "longitude": 4.752,
    "altitude": 395,
    "logements": 1430,
    "logementsMaison": 85,
    "prixM2Moyen": 3280,
    "menuisiersRGE": 2,
    "tauxRenovation": "2.4",
    "intercommunalite": "Communauté de Communes de la Vallée du Garon",
    "canton": "Canton de Montagny",
    "distanceLyon": 16.3,
    "windExposure": "Modéré (Protégé par les collines ou en fond de vallée)",
    "secteurSauvegarde": false,
    "profilCommune": "commune ou village résidentiel du Rhône",
    "marcheImmobilier": "intermédiaire et stable",
    "tauxMaisonLabel": "très majoritairement composé de villas contemporaines et maisons de village"
  },
  {
    "nom": "Lozanne",
    "slug": "lozanne",
    "codeInsee": "69121",
    "codePostal": "69380",
    "population": 3182,
    "latitude": 45.853,
    "longitude": 4.6846,
    "altitude": 183,
    "logements": 1414,
    "logementsMaison": 70,
    "prixM2Moyen": 3350,
    "menuisiersRGE": 2,
    "tauxRenovation": "2.6",
    "intercommunalite": "Communauté de Communes des Monts du Lyonnais",
    "canton": "Canton de Lozanne",
    "distanceLyon": 15.3,
    "windExposure": "Élevé (Monts du Lyonnais et coteaux exposés)",
    "secteurSauvegarde": false,
    "profilCommune": "commune ou village résidentiel du Rhône",
    "marcheImmobilier": "intermédiaire et stable",
    "tauxMaisonLabel": "principalement composé de maisons individuelles et pavillons"
  },
  {
    "nom": "Lissieu",
    "slug": "lissieu",
    "codeInsee": "69117",
    "codePostal": "69380",
    "population": 3181,
    "latitude": 45.8582,
    "longitude": 4.7496,
    "altitude": 250,
    "logements": 1414,
    "logementsMaison": 71,
    "prixM2Moyen": 3460,
    "menuisiersRGE": 4,
    "tauxRenovation": "2.5",
    "intercommunalite": "Communauté de Communes des Monts du Lyonnais",
    "canton": "Canton de Lissieu",
    "distanceLyon": 12.4,
    "windExposure": "Modéré (Protégé par les collines ou en fond de vallée)",
    "secteurSauvegarde": false,
    "profilCommune": "commune ou village résidentiel du Rhône",
    "marcheImmobilier": "intermédiaire et stable",
    "tauxMaisonLabel": "principalement composé de maisons individuelles et pavillons"
  },
  {
    "nom": "Toussieu",
    "slug": "toussieu",
    "codeInsee": "69298",
    "codePostal": "69780",
    "population": 3177,
    "latitude": 45.6585,
    "longitude": 4.9819,
    "altitude": 221,
    "logements": 1412,
    "logementsMaison": 60,
    "prixM2Moyen": 3150,
    "menuisiersRGE": 4,
    "tauxRenovation": "2.6",
    "intercommunalite": "Communauté de Communes des Monts du Lyonnais",
    "canton": "Canton de Toussieu",
    "distanceLyon": 16.3,
    "windExposure": "Modéré (Plaine de l'Est Lyonnais)",
    "secteurSauvegarde": false,
    "profilCommune": "commune ou village résidentiel du Rhône",
    "marcheImmobilier": "intermédiaire et stable",
    "tauxMaisonLabel": "principalement composé de maisons individuelles et pavillons"
  },
  {
    "nom": "Solaize",
    "slug": "solaize",
    "codeInsee": "69296",
    "codePostal": "69360",
    "population": 3144,
    "latitude": 45.6462,
    "longitude": 4.8331,
    "altitude": 219,
    "logements": 1397,
    "logementsMaison": 70,
    "prixM2Moyen": 3410,
    "menuisiersRGE": 4,
    "tauxRenovation": "2.1",
    "intercommunalite": "Métropole de Lyon",
    "canton": "Canton de Solaize",
    "distanceLyon": 13.1,
    "windExposure": "Modéré (Protégé par les collines ou en fond de vallée)",
    "secteurSauvegarde": false,
    "profilCommune": "commune ou village résidentiel du Rhône",
    "marcheImmobilier": "intermédiaire et stable",
    "tauxMaisonLabel": "principalement composé de maisons individuelles et pavillons"
  },
  {
    "nom": "Sérézin-du-Rhône",
    "slug": "serezin-du-rhone",
    "codeInsee": "69294",
    "codePostal": "69360",
    "population": 3133,
    "latitude": 45.6285,
    "longitude": 4.8248,
    "altitude": 150,
    "logements": 1392,
    "logementsMaison": 68,
    "prixM2Moyen": 3370,
    "menuisiersRGE": 3,
    "tauxRenovation": "2.1",
    "intercommunalite": "Communauté de Communes du Pays de l'Ozon",
    "canton": "Canton de Sérézin-du-Rhône",
    "distanceLyon": 15.1,
    "windExposure": "Modéré (Protégé par les collines ou en fond de vallée)",
    "secteurSauvegarde": false,
    "profilCommune": "commune ou village résidentiel du Rhône",
    "marcheImmobilier": "intermédiaire et stable",
    "tauxMaisonLabel": "principalement composé de maisons individuelles et pavillons"
  },
  {
    "nom": "Saint-Germain-au-Mont-d'Or",
    "slug": "saint-germain-au-mont-d-or",
    "codeInsee": "69207",
    "codePostal": "69650",
    "population": 3124,
    "latitude": 45.8842,
    "longitude": 4.8036,
    "altitude": 322,
    "logements": 1388,
    "logementsMaison": 82,
    "prixM2Moyen": 3530,
    "menuisiersRGE": 4,
    "tauxRenovation": "2.9",
    "intercommunalite": "Communauté de Communes des Monts du Lyonnais",
    "canton": "Canton de Saint-Germain-au-Mont-d'Or",
    "distanceLyon": 13.6,
    "windExposure": "Modéré (Protégé par les collines ou en fond de vallée)",
    "secteurSauvegarde": true,
    "profilCommune": "commune ou village résidentiel du Rhône",
    "marcheImmobilier": "intermédiaire et stable",
    "tauxMaisonLabel": "très majoritairement composé de villas contemporaines et maisons de village"
  },
  {
    "nom": "Fontaines-Saint-Martin",
    "slug": "fontaines-saint-martin",
    "codeInsee": "69087",
    "codePostal": "69270",
    "population": 3098,
    "latitude": 45.8445,
    "longitude": 4.8521,
    "altitude": 265,
    "logements": 1377,
    "logementsMaison": 68,
    "prixM2Moyen": 3470,
    "menuisiersRGE": 3,
    "tauxRenovation": "2.8",
    "intercommunalite": "Communauté de Communes des Monts du Lyonnais",
    "canton": "Canton de Fontaines-Saint-Martin",
    "distanceLyon": 9,
    "windExposure": "Modéré (Protégé par les collines ou en fond de vallée)",
    "secteurSauvegarde": false,
    "profilCommune": "commune ou village résidentiel du Rhône",
    "marcheImmobilier": "intermédiaire et stable",
    "tauxMaisonLabel": "principalement composé de maisons individuelles et pavillons"
  },
  {
    "nom": "Albigny-sur-Saône",
    "slug": "albigny-sur-saone",
    "codeInsee": "69003",
    "codePostal": "69250",
    "population": 3057,
    "latitude": 45.8666,
    "longitude": 4.8284,
    "altitude": 150,
    "logements": 1359,
    "logementsMaison": 67,
    "prixM2Moyen": 3470,
    "menuisiersRGE": 3,
    "tauxRenovation": "2.4",
    "intercommunalite": "Communauté de Communes des Monts du Lyonnais",
    "canton": "Canton de Albigny-sur-Saône",
    "distanceLyon": 11.4,
    "windExposure": "Modéré (Protégé par les collines ou en fond de vallée)",
    "secteurSauvegarde": false,
    "profilCommune": "commune ou village résidentiel du Rhône",
    "marcheImmobilier": "intermédiaire et stable",
    "tauxMaisonLabel": "principalement composé de maisons individuelles et pavillons"
  },
  {
    "nom": "Cailloux-sur-Fontaines",
    "slug": "cailloux-sur-fontaines",
    "codeInsee": "69033",
    "codePostal": "69270",
    "population": 2989,
    "latitude": 45.8592,
    "longitude": 4.8817,
    "altitude": 176,
    "logements": 1328,
    "logementsMaison": 69,
    "prixM2Moyen": 3310,
    "menuisiersRGE": 4,
    "tauxRenovation": "2.6",
    "intercommunalite": "Communauté de Communes des Monts du Lyonnais",
    "canton": "Canton de Cailloux-sur-Fontaines",
    "distanceLyon": 11.2,
    "windExposure": "Modéré (Protégé par les collines ou en fond de vallée)",
    "secteurSauvegarde": false,
    "profilCommune": "commune ou village résidentiel du Rhône",
    "marcheImmobilier": "intermédiaire et stable",
    "tauxMaisonLabel": "principalement composé de maisons individuelles et pavillons"
  },
  {
    "nom": "Chasselay",
    "slug": "chasselay",
    "codeInsee": "69049",
    "codePostal": "69380",
    "population": 2973,
    "latitude": 45.8733,
    "longitude": 4.7699,
    "altitude": 181,
    "logements": 1321,
    "logementsMaison": 62,
    "prixM2Moyen": 3590,
    "menuisiersRGE": 4,
    "tauxRenovation": "2.7",
    "intercommunalite": "Communauté de Communes des Monts du Lyonnais",
    "canton": "Canton de Chasselay",
    "distanceLyon": 13.2,
    "windExposure": "Modéré (Protégé par les collines ou en fond de vallée)",
    "secteurSauvegarde": false,
    "profilCommune": "commune ou village résidentiel du Rhône",
    "marcheImmobilier": "intermédiaire et stable",
    "tauxMaisonLabel": "principalement composé de maisons individuelles et pavillons"
  },
  {
    "nom": "Pollionnay",
    "slug": "pollionnay",
    "codeInsee": "69154",
    "codePostal": "69290",
    "population": 2958,
    "latitude": 45.7707,
    "longitude": 4.6585,
    "altitude": 177,
    "logements": 1315,
    "logementsMaison": 70,
    "prixM2Moyen": 3340,
    "menuisiersRGE": 3,
    "tauxRenovation": "2.2",
    "intercommunalite": "Communauté de Communes des Vallons du Lyonnais",
    "canton": "Canton de Pollionnay",
    "distanceLyon": 13.8,
    "windExposure": "Élevé (Monts du Lyonnais et coteaux exposés)",
    "secteurSauvegarde": false,
    "profilCommune": "commune ou village résidentiel du Rhône",
    "marcheImmobilier": "intermédiaire et stable",
    "tauxMaisonLabel": "principalement composé de maisons individuelles et pavillons"
  },
  {
    "nom": "Colombier-Saugnieu",
    "slug": "colombier-saugnieu",
    "codeInsee": "69299",
    "codePostal": "69124",
    "population": 2874,
    "latitude": 45.7174,
    "longitude": 5.1084,
    "altitude": 186,
    "logements": 1277,
    "logementsMaison": 67,
    "prixM2Moyen": 3200,
    "menuisiersRGE": 2,
    "tauxRenovation": "2.2",
    "intercommunalite": "Communauté de Communes des Monts du Lyonnais",
    "canton": "Canton de Colombier-Saugnieu",
    "distanceLyon": 21.8,
    "windExposure": "Modéré (Plaine de l'Est Lyonnais)",
    "secteurSauvegarde": false,
    "profilCommune": "commune ou village résidentiel du Rhône",
    "marcheImmobilier": "intermédiaire et stable",
    "tauxMaisonLabel": "principalement composé de maisons individuelles et pavillons"
  },
  {
    "nom": "Ampuis",
    "slug": "ampuis",
    "codeInsee": "69007",
    "codePostal": "69420",
    "population": 2769,
    "latitude": 45.5034,
    "longitude": 4.8079,
    "altitude": 229,
    "logements": 1231,
    "logementsMaison": 68,
    "prixM2Moyen": 3480,
    "menuisiersRGE": 4,
    "tauxRenovation": "2.7",
    "intercommunalite": "Communauté de Communes des Monts du Lyonnais",
    "canton": "Canton de Ampuis",
    "distanceLyon": 29.1,
    "windExposure": "Modéré (Protégé par les collines ou en fond de vallée)",
    "secteurSauvegarde": false,
    "profilCommune": "commune ou village résidentiel du Rhône",
    "marcheImmobilier": "intermédiaire et stable",
    "tauxMaisonLabel": "principalement composé de maisons individuelles et pavillons"
  },
  {
    "nom": "Loire-sur-Rhône",
    "slug": "loire-sur-rhone",
    "codeInsee": "69118",
    "codePostal": "69700",
    "population": 2746,
    "latitude": 45.5482,
    "longitude": 4.7847,
    "altitude": 150,
    "logements": 1220,
    "logementsMaison": 66,
    "prixM2Moyen": 3500,
    "menuisiersRGE": 2,
    "tauxRenovation": "2.1",
    "intercommunalite": "Communauté de Communes des Monts du Lyonnais",
    "canton": "Canton de Loire-sur-Rhône",
    "distanceLyon": 24.3,
    "windExposure": "Modéré (Protégé par les collines ou en fond de vallée)",
    "secteurSauvegarde": false,
    "profilCommune": "commune ou village résidentiel du Rhône",
    "marcheImmobilier": "intermédiaire et stable",
    "tauxMaisonLabel": "principalement composé de maisons individuelles et pavillons"
  },
  {
    "nom": "Dommartin",
    "slug": "dommartin",
    "codeInsee": "69076",
    "codePostal": "69380",
    "population": 2687,
    "latitude": 45.8372,
    "longitude": 4.7122,
    "altitude": 150,
    "logements": 1194,
    "logementsMaison": 64,
    "prixM2Moyen": 3590,
    "menuisiersRGE": 3,
    "tauxRenovation": "2.2",
    "intercommunalite": "Communauté de Communes des Monts du Lyonnais",
    "canton": "Canton de Dommartin",
    "distanceLyon": 12.6,
    "windExposure": "Modéré (Protégé par les collines ou en fond de vallée)",
    "secteurSauvegarde": false,
    "profilCommune": "commune ou village résidentiel du Rhône",
    "marcheImmobilier": "intermédiaire et stable",
    "tauxMaisonLabel": "principalement composé de maisons individuelles et pavillons"
  },
  {
    "nom": "Taluyers",
    "slug": "taluyers",
    "codeInsee": "69241",
    "codePostal": "69440",
    "population": 2686,
    "latitude": 45.6343,
    "longitude": 4.7265,
    "altitude": 185,
    "logements": 1194,
    "logementsMaison": 60,
    "prixM2Moyen": 3490,
    "menuisiersRGE": 2,
    "tauxRenovation": "2.4",
    "intercommunalite": "Communauté de Communes des Monts du Lyonnais",
    "canton": "Canton de Taluyers",
    "distanceLyon": 16.7,
    "windExposure": "Modéré (Protégé par les collines ou en fond de vallée)",
    "secteurSauvegarde": false,
    "profilCommune": "commune ou village résidentiel du Rhône",
    "marcheImmobilier": "intermédiaire et stable",
    "tauxMaisonLabel": "principalement composé de maisons individuelles et pavillons"
  },
  {
    "nom": "Orliénas",
    "slug": "orlienas",
    "codeInsee": "69148",
    "codePostal": "69530",
    "population": 2675,
    "latitude": 45.6609,
    "longitude": 4.7207,
    "altitude": 171,
    "logements": 1189,
    "logementsMaison": 64,
    "prixM2Moyen": 3350,
    "menuisiersRGE": 2,
    "tauxRenovation": "2.7",
    "intercommunalite": "Communauté de Communes de la Vallée du Garon",
    "canton": "Canton de Orliénas",
    "distanceLyon": 14.5,
    "windExposure": "Modéré (Protégé par les collines ou en fond de vallée)",
    "secteurSauvegarde": false,
    "profilCommune": "commune ou village résidentiel du Rhône",
    "marcheImmobilier": "intermédiaire et stable",
    "tauxMaisonLabel": "principalement composé de maisons individuelles et pavillons"
  },
  {
    "nom": "Couzon-au-Mont-d'Or",
    "slug": "couzon-au-mont-d-or",
    "codeInsee": "69068",
    "codePostal": "69270",
    "population": 2619,
    "latitude": 45.8479,
    "longitude": 4.8214,
    "altitude": 347,
    "logements": 1164,
    "logementsMaison": 76,
    "prixM2Moyen": 3440,
    "menuisiersRGE": 4,
    "tauxRenovation": "2.6",
    "intercommunalite": "Communauté de Communes des Monts du Lyonnais",
    "canton": "Canton de Couzon-au-Mont-d'Or",
    "distanceLyon": 9.4,
    "windExposure": "Modéré (Protégé par les collines ou en fond de vallée)",
    "secteurSauvegarde": true,
    "profilCommune": "commune ou village résidentiel du Rhône",
    "marcheImmobilier": "intermédiaire et stable",
    "tauxMaisonLabel": "principalement composé de maisons individuelles et pavillons"
  },
  {
    "nom": "Pommiers",
    "slug": "pommiers",
    "codeInsee": "69156",
    "codePostal": "69480",
    "population": 2618,
    "latitude": 45.9581,
    "longitude": 4.6928,
    "altitude": 160,
    "logements": 1164,
    "logementsMaison": 71,
    "prixM2Moyen": 3280,
    "menuisiersRGE": 2,
    "tauxRenovation": "2.8",
    "intercommunalite": "Communauté de Communes Beaujolais Pierres Dorées",
    "canton": "Canton de Pommiers",
    "distanceLyon": 24.2,
    "windExposure": "Élevé (Monts du Lyonnais et coteaux exposés)",
    "secteurSauvegarde": false,
    "profilCommune": "commune ou village résidentiel du Rhône",
    "marcheImmobilier": "intermédiaire et stable",
    "tauxMaisonLabel": "principalement composé de maisons individuelles et pavillons"
  },
  {
    "nom": "Saint-Pierre-la-Palud",
    "slug": "saint-pierre-la-palud",
    "codeInsee": "69231",
    "codePostal": "69210",
    "population": 2616,
    "latitude": 45.7833,
    "longitude": 4.6163,
    "altitude": 150,
    "logements": 1163,
    "logementsMaison": 63,
    "prixM2Moyen": 3440,
    "menuisiersRGE": 2,
    "tauxRenovation": "2.9",
    "intercommunalite": "Communauté de Communes du Pays de L'Arbresle",
    "canton": "Canton de Saint-Pierre-la-Palud",
    "distanceLyon": 17.1,
    "windExposure": "Élevé (Monts du Lyonnais et coteaux exposés)",
    "secteurSauvegarde": false,
    "profilCommune": "commune ou village résidentiel du Rhône",
    "marcheImmobilier": "intermédiaire et stable",
    "tauxMaisonLabel": "principalement composé de maisons individuelles et pavillons"
  },
  {
    "nom": "Sain-Bel",
    "slug": "sain-bel",
    "codeInsee": "69171",
    "codePostal": "69210",
    "population": 2566,
    "latitude": 45.8115,
    "longitude": 4.6017,
    "altitude": 217,
    "logements": 1140,
    "logementsMaison": 68,
    "prixM2Moyen": 3550,
    "menuisiersRGE": 4,
    "tauxRenovation": "2.3",
    "intercommunalite": "Communauté de Communes du Pays de L'Arbresle",
    "canton": "Canton de Sain-Bel",
    "distanceLyon": 18.9,
    "windExposure": "Élevé (Monts du Lyonnais et coteaux exposés)",
    "secteurSauvegarde": false,
    "profilCommune": "commune ou village résidentiel du Rhône",
    "marcheImmobilier": "intermédiaire et stable",
    "tauxMaisonLabel": "principalement composé de maisons individuelles et pavillons"
  },
  {
    "nom": "Sathonay-Village",
    "slug": "sathonay-village",
    "codeInsee": "69293",
    "codePostal": "69580",
    "population": 2412,
    "latitude": 45.8394,
    "longitude": 4.8858,
    "altitude": 272,
    "logements": 1072,
    "logementsMaison": 69,
    "prixM2Moyen": 3110,
    "menuisiersRGE": 3,
    "tauxRenovation": "2.6",
    "intercommunalite": "Communauté de Communes des Monts du Lyonnais",
    "canton": "Canton de Sathonay-Village",
    "distanceLyon": 9.2,
    "windExposure": "Modéré (Protégé par les collines ou en fond de vallée)",
    "secteurSauvegarde": false,
    "profilCommune": "commune ou village résidentiel du Rhône",
    "marcheImmobilier": "intermédiaire et stable",
    "tauxMaisonLabel": "principalement composé de maisons individuelles et pavillons"
  },
  {
    "nom": "Fleurieux-sur-l'Arbresle",
    "slug": "fleurieux-sur-l-arbresle",
    "codeInsee": "69086",
    "codePostal": "69210",
    "population": 2361,
    "latitude": 45.8406,
    "longitude": 4.6484,
    "altitude": 150,
    "logements": 1049,
    "logementsMaison": 67,
    "prixM2Moyen": 3190,
    "menuisiersRGE": 2,
    "tauxRenovation": "2.7",
    "intercommunalite": "Communauté de Communes du Pays de L'Arbresle",
    "canton": "Canton de Fleurieux-sur-l'Arbresle",
    "distanceLyon": 16.8,
    "windExposure": "Élevé (Monts du Lyonnais et coteaux exposés)",
    "secteurSauvegarde": false,
    "profilCommune": "commune ou village résidentiel du Rhône",
    "marcheImmobilier": "intermédiaire et stable",
    "tauxMaisonLabel": "principalement composé de maisons individuelles et pavillons"
  },
  {
    "nom": "Bessenay",
    "slug": "bessenay",
    "codeInsee": "69021",
    "codePostal": "69690",
    "population": 2331,
    "latitude": 45.7712,
    "longitude": 4.5484,
    "altitude": 254,
    "logements": 1036,
    "logementsMaison": 69,
    "prixM2Moyen": 3420,
    "menuisiersRGE": 3,
    "tauxRenovation": "2.2",
    "intercommunalite": "Communauté de Communes des Monts du Lyonnais",
    "canton": "Canton de Bessenay",
    "distanceLyon": 22.3,
    "windExposure": "Élevé (Monts du Lyonnais et coteaux exposés)",
    "secteurSauvegarde": false,
    "profilCommune": "commune ou village résidentiel du Rhône",
    "marcheImmobilier": "intermédiaire et stable",
    "tauxMaisonLabel": "principalement composé de maisons individuelles et pavillons"
  },
  {
    "nom": "Saint-Étienne-des-Oullières",
    "slug": "saint-etienne-des-oullieres",
    "codeInsee": "69197",
    "codePostal": "69460",
    "population": 2264,
    "latitude": 46.0645,
    "longitude": 4.6557,
    "altitude": 150,
    "logements": 1006,
    "logementsMaison": 69,
    "prixM2Moyen": 3380,
    "menuisiersRGE": 3,
    "tauxRenovation": "2.9",
    "intercommunalite": "Communauté de Communes des Monts du Lyonnais",
    "canton": "Canton de Saint-Étienne-des-Oullières",
    "distanceLyon": 36.2,
    "windExposure": "Élevé (Monts du Lyonnais et coteaux exposés)",
    "secteurSauvegarde": false,
    "profilCommune": "commune ou village résidentiel du Rhône",
    "marcheImmobilier": "intermédiaire et stable",
    "tauxMaisonLabel": "principalement composé de maisons individuelles et pavillons"
  },
  {
    "nom": "Morancé",
    "slug": "morance",
    "codeInsee": "69140",
    "codePostal": "69480",
    "population": 2261,
    "latitude": 45.8938,
    "longitude": 4.7016,
    "altitude": 255,
    "logements": 1005,
    "logementsMaison": 70,
    "prixM2Moyen": 3480,
    "menuisiersRGE": 2,
    "tauxRenovation": "2.9",
    "intercommunalite": "Communauté de Communes Beaujolais Pierres Dorées",
    "canton": "Canton de Morancé",
    "distanceLyon": 17.8,
    "windExposure": "Modéré (Protégé par les collines ou en fond de vallée)",
    "secteurSauvegarde": false,
    "profilCommune": "commune ou village résidentiel du Rhône",
    "marcheImmobilier": "intermédiaire et stable",
    "tauxMaisonLabel": "principalement composé de maisons individuelles et pavillons"
  },
  {
    "nom": "Châtillon",
    "slug": "chatillon",
    "codeInsee": "69050",
    "codePostal": "69380",
    "population": 2252,
    "latitude": 45.872,
    "longitude": 4.6487,
    "altitude": 182,
    "logements": 1001,
    "logementsMaison": 63,
    "prixM2Moyen": 3190,
    "menuisiersRGE": 2,
    "tauxRenovation": "2.8",
    "intercommunalite": "Communauté de Communes des Monts du Lyonnais",
    "canton": "Canton de Châtillon",
    "distanceLyon": 18.8,
    "windExposure": "Élevé (Monts du Lyonnais et coteaux exposés)",
    "secteurSauvegarde": false,
    "profilCommune": "commune ou village résidentiel du Rhône",
    "marcheImmobilier": "intermédiaire et stable",
    "tauxMaisonLabel": "principalement composé de maisons individuelles et pavillons"
  },
  {
    "nom": "Saint-Germain-Nuelles",
    "slug": "saint-germain-nuelles",
    "codeInsee": "69208",
    "codePostal": "69210",
    "population": 2246,
    "latitude": 45.8604,
    "longitude": 4.6167,
    "altitude": 158,
    "logements": 998,
    "logementsMaison": 63,
    "prixM2Moyen": 3480,
    "menuisiersRGE": 3,
    "tauxRenovation": "2.3",
    "intercommunalite": "Communauté de Communes du Pays de L'Arbresle",
    "canton": "Canton de Saint-Germain-Nuelles",
    "distanceLyon": 20.1,
    "windExposure": "Élevé (Monts du Lyonnais et coteaux exposés)",
    "secteurSauvegarde": false,
    "profilCommune": "commune ou village résidentiel du Rhône",
    "marcheImmobilier": "intermédiaire et stable",
    "tauxMaisonLabel": "principalement composé de maisons individuelles et pavillons"
  },
  {
    "nom": "Bully",
    "slug": "bully",
    "codeInsee": "69032",
    "codePostal": "69210",
    "population": 2213,
    "latitude": 45.8595,
    "longitude": 4.5786,
    "altitude": 158,
    "logements": 984,
    "logementsMaison": 69,
    "prixM2Moyen": 3230,
    "menuisiersRGE": 2,
    "tauxRenovation": "2.4",
    "intercommunalite": "Communauté de Communes du Pays de L'Arbresle",
    "canton": "Canton de Bully",
    "distanceLyon": 22.6,
    "windExposure": "Élevé (Monts du Lyonnais et coteaux exposés)",
    "secteurSauvegarde": false,
    "profilCommune": "commune ou village résidentiel du Rhône",
    "marcheImmobilier": "intermédiaire et stable",
    "tauxMaisonLabel": "principalement composé de maisons individuelles et pavillons"
  },
  {
    "nom": "Sainte-Consorce",
    "slug": "sainte-consorce",
    "codeInsee": "69190",
    "codePostal": "69280",
    "population": 2154,
    "latitude": 45.7765,
    "longitude": 4.6959,
    "altitude": 217,
    "logements": 957,
    "logementsMaison": 62,
    "prixM2Moyen": 3410,
    "menuisiersRGE": 3,
    "tauxRenovation": "2.6",
    "intercommunalite": "Communauté de Communes des Monts du Lyonnais",
    "canton": "Canton de Sainte-Consorce",
    "distanceLyon": 10.9,
    "windExposure": "Élevé (Monts du Lyonnais et coteaux exposés)",
    "secteurSauvegarde": false,
    "profilCommune": "commune ou village résidentiel du Rhône",
    "marcheImmobilier": "intermédiaire et stable",
    "tauxMaisonLabel": "principalement composé de maisons individuelles et pavillons"
  },
  {
    "nom": "Villié-Morgon",
    "slug": "villie-morgon",
    "codeInsee": "69267",
    "codePostal": "69910",
    "population": 2148,
    "latitude": 46.1612,
    "longitude": 4.6621,
    "altitude": 274,
    "logements": 955,
    "logementsMaison": 71,
    "prixM2Moyen": 3290,
    "menuisiersRGE": 3,
    "tauxRenovation": "2.4",
    "intercommunalite": "Communauté de Communes des Monts du Lyonnais",
    "canton": "Canton de Villié-Morgon",
    "distanceLyon": 46.2,
    "windExposure": "Élevé (Monts du Lyonnais et coteaux exposés)",
    "secteurSauvegarde": false,
    "profilCommune": "commune ou village résidentiel du Rhône",
    "marcheImmobilier": "intermédiaire et stable",
    "tauxMaisonLabel": "principalement composé de maisons individuelles et pavillons"
  },
  {
    "nom": "Saint-Laurent-d'Agny",
    "slug": "saint-laurent-d-agny",
    "codeInsee": "69219",
    "codePostal": "69440",
    "population": 2111,
    "latitude": 45.6406,
    "longitude": 4.6828,
    "altitude": 170,
    "logements": 938,
    "logementsMaison": 69,
    "prixM2Moyen": 3210,
    "menuisiersRGE": 3,
    "tauxRenovation": "2.2",
    "intercommunalite": "Communauté de Communes des Monts du Lyonnais",
    "canton": "Canton de Saint-Laurent-d'Agny",
    "distanceLyon": 18.1,
    "windExposure": "Élevé (Monts du Lyonnais et coteaux exposés)",
    "secteurSauvegarde": false,
    "profilCommune": "commune ou village résidentiel du Rhône",
    "marcheImmobilier": "intermédiaire et stable",
    "tauxMaisonLabel": "principalement composé de maisons individuelles et pavillons"
  },
  {
    "nom": "Sourcieux-les-Mines",
    "slug": "sourcieux-les-mines",
    "codeInsee": "69177",
    "codePostal": "69210",
    "population": 2100,
    "latitude": 45.7979,
    "longitude": 4.6311,
    "altitude": 195,
    "logements": 933,
    "logementsMaison": 64,
    "prixM2Moyen": 3350,
    "menuisiersRGE": 4,
    "tauxRenovation": "2.2",
    "intercommunalite": "Communauté de Communes du Pays de L'Arbresle",
    "canton": "Canton de Sourcieux-les-Mines",
    "distanceLyon": 16.3,
    "windExposure": "Élevé (Monts du Lyonnais et coteaux exposés)",
    "secteurSauvegarde": false,
    "profilCommune": "commune ou village résidentiel du Rhône",
    "marcheImmobilier": "intermédiaire et stable",
    "tauxMaisonLabel": "principalement composé de maisons individuelles et pavillons"
  },
  {
    "nom": "Beaujeu",
    "slug": "beaujeu",
    "codeInsee": "69018",
    "codePostal": "69430",
    "population": 2082,
    "latitude": 46.1585,
    "longitude": 4.5802,
    "altitude": 207,
    "logements": 925,
    "logementsMaison": 70,
    "prixM2Moyen": 3310,
    "menuisiersRGE": 4,
    "tauxRenovation": "2.8",
    "intercommunalite": "Communauté de Communes des Monts du Lyonnais",
    "canton": "Canton de Beaujeu",
    "distanceLyon": 48.1,
    "windExposure": "Élevé (Monts du Lyonnais et coteaux exposés)",
    "secteurSauvegarde": true,
    "profilCommune": "commune ou village résidentiel du Rhône",
    "marcheImmobilier": "intermédiaire et stable",
    "tauxMaisonLabel": "principalement composé de maisons individuelles et pavillons"
  },
  {
    "nom": "Lucenay",
    "slug": "lucenay",
    "codeInsee": "69122",
    "codePostal": "69480",
    "population": 2070,
    "latitude": 45.9138,
    "longitude": 4.7095,
    "altitude": 237,
    "logements": 920,
    "logementsMaison": 70,
    "prixM2Moyen": 3550,
    "menuisiersRGE": 2,
    "tauxRenovation": "2.3",
    "intercommunalite": "Communauté de Communes Beaujolais Pierres Dorées",
    "canton": "Canton de Lucenay",
    "distanceLyon": 19.3,
    "windExposure": "Modéré (Protégé par les collines ou en fond de vallée)",
    "secteurSauvegarde": false,
    "profilCommune": "commune ou village résidentiel du Rhône",
    "marcheImmobilier": "intermédiaire et stable",
    "tauxMaisonLabel": "principalement composé de maisons individuelles et pavillons"
  },
  {
    "nom": "Chessy",
    "slug": "chessy",
    "codeInsee": "69056",
    "codePostal": "69380",
    "population": 2055,
    "latitude": 45.8914,
    "longitude": 4.6168,
    "altitude": 150,
    "logements": 913,
    "logementsMaison": 62,
    "prixM2Moyen": 3590,
    "menuisiersRGE": 4,
    "tauxRenovation": "2.1",
    "intercommunalite": "Communauté de Communes des Monts du Lyonnais",
    "canton": "Canton de Chessy",
    "distanceLyon": 22.1,
    "windExposure": "Élevé (Monts du Lyonnais et coteaux exposés)",
    "secteurSauvegarde": false,
    "profilCommune": "commune ou village résidentiel du Rhône",
    "marcheImmobilier": "intermédiaire et stable",
    "tauxMaisonLabel": "principalement composé de maisons individuelles et pavillons"
  },
  {
    "nom": "Sainte-Colombe",
    "slug": "sainte-colombe",
    "codeInsee": "69189",
    "codePostal": "69560",
    "population": 2036,
    "latitude": 45.5247,
    "longitude": 4.8582,
    "altitude": 150,
    "logements": 905,
    "logementsMaison": 67,
    "prixM2Moyen": 3220,
    "menuisiersRGE": 2,
    "tauxRenovation": "2.7",
    "intercommunalite": "Communauté de Communes des Monts du Lyonnais",
    "canton": "Canton de Sainte-Colombe",
    "distanceLyon": 26.7,
    "windExposure": "Modéré (Protégé par les collines ou en fond de vallée)",
    "secteurSauvegarde": false,
    "profilCommune": "commune ou village résidentiel du Rhône",
    "marcheImmobilier": "intermédiaire et stable",
    "tauxMaisonLabel": "principalement composé de maisons individuelles et pavillons"
  },
  {
    "nom": "Saint-Laurent-de-Chamousset",
    "slug": "saint-laurent-de-chamousset",
    "codeInsee": "69220",
    "codePostal": "69930",
    "population": 2017,
    "latitude": 45.7402,
    "longitude": 4.4688,
    "altitude": 184,
    "logements": 896,
    "logementsMaison": 71,
    "prixM2Moyen": 3470,
    "menuisiersRGE": 2,
    "tauxRenovation": "2.7",
    "intercommunalite": "Communauté de Communes des Monts du Lyonnais",
    "canton": "Canton de Saint-Laurent-de-Chamousset",
    "distanceLyon": 28.6,
    "windExposure": "Élevé (Monts du Lyonnais et coteaux exposés)",
    "secteurSauvegarde": false,
    "profilCommune": "commune ou village résidentiel du Rhône",
    "marcheImmobilier": "intermédiaire et stable",
    "tauxMaisonLabel": "principalement composé de maisons individuelles et pavillons"
  },
  {
    "nom": "Saint-Romain-en-Gal",
    "slug": "saint-romain-en-gal",
    "codeInsee": "69235",
    "codePostal": "69560",
    "population": 2001,
    "latitude": 45.5402,
    "longitude": 4.8307,
    "altitude": 159,
    "logements": 889,
    "logementsMaison": 64,
    "prixM2Moyen": 3120,
    "menuisiersRGE": 4,
    "tauxRenovation": "2.9",
    "intercommunalite": "Communauté de Communes des Monts du Lyonnais",
    "canton": "Canton de Saint-Romain-en-Gal",
    "distanceLyon": 24.9,
    "windExposure": "Modéré (Protégé par les collines ou en fond de vallée)",
    "secteurSauvegarde": false,
    "profilCommune": "commune ou village résidentiel du Rhône",
    "marcheImmobilier": "intermédiaire et stable",
    "tauxMaisonLabel": "principalement composé de maisons individuelles et pavillons"
  }
]
